{
  "meta": {
    "code": 200,
    "response_time": {
      "time": 0.433,
      "measure": "seconds"
    },
    "init_time": {
      "time": 0.011,
      "measure": "seconds"
    }
  },
  "notifications": [

  ],
  "response": {
    "brewery": {
      "brewery_id": 129448,
      "brewery_name": "Dageraad Brewing",
      "brewery_slug": "dageraad-brewing",
      "brewery_label": "https://untappd.akamaized.net/site/brewery_logos/brewery-129448_9e147.jpeg",
      "country_name": "Canada",
      "brewery_in_production": 0,
      "is_independent": 1,
      "claimed_status": {
        "is_claimed": true,
        "claimed_slug": "Dageraad",
        "follow_status": false,
        "follower_count": 1050,
        "uid": 1690782,
        "mute_status": "none"
      },
      "beer_count": 28,
      "contact": {
        "twitter": "DageraadBeer",
        "facebook": "https://www.facebook.com/DageraadBrewing",
        "instagram": "",
        "url": "http://dageraadbrewing.com"
      },
      "brewery_type": "Micro Brewery",
      "brewery_type_id": 2,
      "location": {
        "brewery_address": "#114, 3191 Thunderbird Crescent",
        "brewery_city": "Burnaby",
        "brewery_state": "BC",
        "brewery_lat": 49.2559,
        "brewery_lng": -122.921
      },
      "rating": {
        "count": 15297,
        "rating_score": 3.763
      },
      "brewery_description": "A small-batch brewery specializing in Belgian-style beers.",
      "stats": {
        "total_count": 21295,
        "unique_count": 5641,
        "monthly_count": 840,
        "weekly_count": 244,
        "user_count": 0,
        "age_on_service": 1179.510011574074
      },
      "owners": {
        "count": 0,
        "items": [

        ]
      },
      "media": null,
      "checkins": null,
      "beer_list": null,
      "locations": {
        "count": 1,
        "items": [
          {
            "venue": {
              "venue_id": 1692494,
              "venue_name": "Dageraad Brewing",
              "venue_slug": "dageraad-brewing",
              "primary_category": "Nightlife Spot",
              "parent_category_id": "4d4b7105d754a06376d81259",
              "categories": {
                "count": 1,
                "items": [
                  {
                    "category_name": "Brewery",
                    "category_id": "50327c8591d4c4b30a586d5d",
                    "is_primary": true
                  }
                ]
              },
              "location": {
                "venue_address": "114 - 3191 Thunderbird Cres",
                "venue_city": "Burnaby",
                "venue_state": "BC",
                "venue_country": "Canada",
                "lat": 49.256,
                "lng": -122.922
              },
              "contact": {
                "twitter": "@dageraadbeer",
                "venue_url": "http://dageraadbrewing.com"
              },
              "foursquare": {
                "foursquare_id": "537237e3498e417222206af0",
                "foursquare_url": "http://4sq.com/1li4iu8"
              },
              "venue_icon": {
                "sm": "https://ss3.4sqi.net/img/categories_v2/food/brewery_bg_64.png",
                "md": "https://ss3.4sqi.net/img/categories_v2/food/brewery_bg_88.png",
                "lg": "https://ss3.4sqi.net/img/categories_v2/food/brewery_bg_88.png"
              },
              "is_verified": false
            }
          }
        ]
      }
    }
  }
}