{"meta":{"code":200,"response_time":{"time":0.322,"measure":"seconds"},"init_time":{"time":0,"measure":"seconds"}},"notifications":[],"response":{"brewery":{"brewery_id":531798,"brewery_name":"Wooden Axe Brewing Co","brewery_slug":"wooden-axe-brewing-co","brewery_page_url":"\/WoodenAxeBrewingCo","brewery_label":"https:\/\/assets.untappd.com\/site\/brewery_logos\/brewery-531798_e625c.jpeg","brewery_label_hd":"https:\/\/assets.untappd.com\/site\/brewery_logos_hd\/brewery-531798_7715c_hd.jpeg","country_name":"Australia","brewery_in_production":0,"is_independent":1,"claimed_status":{"is_claimed":true,"claimed_slug":"WoodenAxeBrewingCo","follow_status":false,"follower_count":5,"uid":10191865,"mute_status":"none"},"beer_count":3,"contact":{"twitter":"","facebook":"","instagram":"woodenaxebrewingco","url":"http:\/\/www.woodenaxe.beer"},"brewery_type":"Contract Brewery","brewery_type_id":10,"location":{"brewery_address":null,"brewery_city":"","brewery_state":"","brewery_lat":0,"brewery_lng":0},"rating":{"count":327,"rating_score":3.88},"brewery_description":"","stats":{"total_count":368,"unique_count":284,"monthly_count":42,"weekly_count":1,"user_count":0,"age_on_service":468.92375},"owners":{"count":0,"items":[]},"media":{"count":15,"items":[{"photo_id":533678753,"photo":{"photo_img_sm":"https:\/\/images.untp.beer\/crop?width=200&height=200&stripmeta=true&url=https:\/\/untappd.s3.amazonaws.com\/photos\/2024_03_25\/ad532c3192b7391f8ac51fd9b7449ae8_c_1366544633_raw.jpg","photo_img_md":"https:\/\/images.untp.beer\/crop?width=640&height=640&stripmeta=true&url=https:\/\/untappd.s3.amazonaws.com\/photos\/2024_03_25\/ad532c3192b7391f8ac51fd9b7449ae8_c_1366544633_raw.jpg","photo_img_lg":"https:\/\/images.untp.beer\/crop?width=1280&height=1280&stripmeta=true&url=https:\/\/untappd.s3.amazonaws.com\/photos\/2024_03_25\/ad532c3192b7391f8ac51fd9b7449ae8_c_1366544633_raw.jpg","photo_img_og":"https:\/\/assets.untappd.com\/photos\/2024_03_25\/ad532c3192b7391f8ac51fd9b7449ae8_c_1366544633_raw.jpg"},"created_at":"Mon, 25 Mar 2024 08:11:43 +0000","checkin_id":1366544633,"beer":{"bid":5682538,"beer_name":"Off In the Woods","beer_abv":6.5,"beer_label":"https:\/\/assets.untappd.com\/site\/beer_logos\/beer-5682538_b03d4_sm.jpeg","beer_style":"IPA - American"},"brewery":{"brewery_id":531798,"brewery_name":"Wooden Axe Brewing Co","brewery_slug":"wooden-axe-brewing-co","brewery_page_url":"\/WoodenAxeBrewingCo","brewery_type":"Contract Brewery","brewery_label":"https:\/\/assets.untappd.com\/site\/brewery_logos\/brewery-531798_e625c.jpeg","country_name":"Australia","contact":{"twitter":"","facebook":"","instagram":"woodenaxebrewingco","url":"http:\/\/www.woodenaxe.beer"},"location":{"brewery_city":"","brewery_state":"","lat":0,"lng":0},"brewery_active":1},"user":{"uid":8777114,"user_name":"john_vendel_8761","first_name":"John","last_name":"Vendel","user_avatar":"https:\/\/assets.untappd.com\/profile\/8b5d580270d7f81c41e92fc3f124455d_100x100.jpg","is_private":0},"venue":{"venue_id":9917985,"venue_name":"Untappd at Home","venue_slug":"at-home","primary_category":null,"parent_category_id":"4e67e38e036454776db1fb3a","categories":{"count":1,"items":[{"category_key":"home_private","category_name":"Home (private)","category_id":"4bf58dd8d48988d103941735","is_primary":true}]},"location":{"venue_address":"","venue_city":"","venue_state":"NC","lat":34.2347,"lng":-77.9482},"contact":{"twitter":"","venue_url":""},"foursquare":{"foursquare_id":"5e7b4d99c91df60008e8b168","foursquare_url":"https:\/\/4sq.com\/3bDWYuq"},"venue_icon":{"sm":"https:\/\/assets.untappd.com\/venuelogos\/venue_9917985_b3a5d245_bg_64.png","md":"https:\/\/assets.untappd.com\/venuelogos\/venue_9917985_b3a5d245_bg_88.png","lg":"https:\/\/assets.untappd.com\/venuelogos\/venue_9917985_b3a5d245_bg_176.png?v=1"},"is_verified":1}},{"photo_id":533528579,"photo":{"photo_img_sm":"https:\/\/images.untp.beer\/crop?width=200&height=200&stripmeta=true&url=https:\/\/untappd.s3.amazonaws.com\/photos\/2024_03_24\/ed804361191d3d81a14b02b1449d865d_c_1366268335_raw.jpg","photo_img_md":"https:\/\/images.untp.beer\/crop?width=640&height=640&stripmeta=true&url=https:\/\/untappd.s3.amazonaws.com\/photos\/2024_03_24\/ed804361191d3d81a14b02b1449d865d_c_1366268335_raw.jpg","photo_img_lg":"https:\/\/images.untp.beer\/crop?width=1280&height=1280&stripmeta=true&url=https:\/\/untappd.s3.amazonaws.com\/photos\/2024_03_24\/ed804361191d3d81a14b02b1449d865d_c_1366268335_raw.jpg","photo_img_og":"https:\/\/assets.untappd.com\/photos\/2024_03_24\/ed804361191d3d81a14b02b1449d865d_c_1366268335_raw.jpg"},"created_at":"Sun, 24 Mar 2024 11:39:39 +0000","checkin_id":1366268335,"beer":{"bid":5682538,"beer_name":"Off In the Woods","beer_abv":6.5,"beer_label":"https:\/\/assets.untappd.com\/site\/beer_logos\/beer-5682538_b03d4_sm.jpeg","beer_style":"IPA - American"},"brewery":{"brewery_id":531798,"brewery_name":"Wooden Axe Brewing Co","brewery_slug":"wooden-axe-brewing-co","brewery_page_url":"\/WoodenAxeBrewingCo","brewery_type":"Contract Brewery","brewery_label":"https:\/\/assets.untappd.com\/site\/brewery_logos\/brewery-531798_e625c.jpeg","country_name":"Australia","contact":{"twitter":"","facebook":"","instagram":"woodenaxebrewingco","url":"http:\/\/www.woodenaxe.beer"},"location":{"brewery_city":"","brewery_state":"","lat":0,"lng":0},"brewery_active":1},"user":{"uid":928722,"user_name":"dr_keg","first_name":"Tom","last_name":"Wellings","user_avatar":"https:\/\/assets.untappd.com\/profile\/d7ba47ebe4cc9bdb539c78ff9aab8ec4_100x100.jpg","is_private":0},"venue":{"venue_id":9917985,"venue_name":"Untappd at Home","venue_slug":"at-home","primary_category":null,"parent_category_id":"4e67e38e036454776db1fb3a","categories":{"count":1,"items":[{"category_key":"home_private","category_name":"Home (private)","category_id":"4bf58dd8d48988d103941735","is_primary":true}]},"location":{"venue_address":"","venue_city":"","venue_state":"NC","lat":34.2347,"lng":-77.9482},"contact":{"twitter":"","venue_url":""},"foursquare":{"foursquare_id":"5e7b4d99c91df60008e8b168","foursquare_url":"https:\/\/4sq.com\/3bDWYuq"},"venue_icon":{"sm":"https:\/\/assets.untappd.com\/venuelogos\/venue_9917985_b3a5d245_bg_64.png","md":"https:\/\/assets.untappd.com\/venuelogos\/venue_9917985_b3a5d245_bg_88.png","lg":"https:\/\/assets.untappd.com\/venuelogos\/venue_9917985_b3a5d245_bg_176.png?v=1"},"is_verified":1}},{"photo_id":533518288,"photo":{"photo_img_sm":"https:\/\/images.untp.beer\/crop?width=200&height=200&stripmeta=true&url=https:\/\/untappd.s3.amazonaws.com\/photos\/2024_03_24\/f4ae53f9fe0dc047ad948595aa4a2ef9_c_1366250679_raw.jpg","photo_img_md":"https:\/\/images.untp.beer\/crop?width=640&height=640&stripmeta=true&url=https:\/\/untappd.s3.amazonaws.com\/photos\/2024_03_24\/f4ae53f9fe0dc047ad948595aa4a2ef9_c_1366250679_raw.jpg","photo_img_lg":"https:\/\/images.untp.beer\/crop?width=1280&height=1280&stripmeta=true&url=https:\/\/untappd.s3.amazonaws.com\/photos\/2024_03_24\/f4ae53f9fe0dc047ad948595aa4a2ef9_c_1366250679_raw.jpg","photo_img_og":"https:\/\/assets.untappd.com\/photos\/2024_03_24\/f4ae53f9fe0dc047ad948595aa4a2ef9_c_1366250679_raw.jpg"},"created_at":"Sun, 24 Mar 2024 06:17:37 +0000","checkin_id":1366250679,"beer":{"bid":5682538,"beer_name":"Off In the Woods","beer_abv":6.5,"beer_label":"https:\/\/assets.untappd.com\/site\/beer_logos\/beer-5682538_b03d4_sm.jpeg","beer_style":"IPA - American"},"brewery":{"brewery_id":531798,"brewery_name":"Wooden Axe Brewing Co","brewery_slug":"wooden-axe-brewing-co","brewery_page_url":"\/WoodenAxeBrewingCo","brewery_type":"Contract Brewery","brewery_label":"https:\/\/assets.untappd.com\/site\/brewery_logos\/brewery-531798_e625c.jpeg","country_name":"Australia","contact":{"twitter":"","facebook":"","instagram":"woodenaxebrewingco","url":"http:\/\/www.woodenaxe.beer"},"location":{"brewery_city":"","brewery_state":"","lat":0,"lng":0},"brewery_active":1},"user":{"uid":1447073,"user_name":"Mattbell1","first_name":"Matt","last_name":"Bell","user_avatar":"https:\/\/assets.untappd.com\/profile\/f47214b840cdcc2782452bbc956a7dfe_100x100.jpg","is_private":0},"venue":{"venue_id":178038,"venue_name":"The Greengate Hotel","venue_slug":"the-greengate-hotel","primary_category":"Dining and Drinking","parent_category_id":"63be6904847c3692a84b9bb5","categories":{"count":1,"items":[{"category_key":"pub","category_name":"Pub","category_id":"4bf58dd8d48988d11b941735","is_primary":true}]},"location":{"venue_address":"655 Pacific Hwy","venue_city":"","venue_state":"New South Wales","lat":-33.763,"lng":151.156},"contact":{"twitter":"","venue_url":"https:\/\/www.greengatehotel.com.au"},"foursquare":{"foursquare_id":"4b0f45ebf964a5200b6123e3","foursquare_url":"http:\/\/4sq.com\/7PtIAe"},"venue_icon":{"sm":"https:\/\/ss3.4sqi.net\/img\/categories_v2\/nightlife\/pub_bg_64.png","md":"https:\/\/ss3.4sqi.net\/img\/categories_v2\/nightlife\/pub_bg_88.png","lg":"https:\/\/ss3.4sqi.net\/img\/categories_v2\/nightlife\/pub_bg_512.png"},"is_verified":0}},{"photo_id":533393286,"photo":{"photo_img_sm":"https:\/\/images.untp.beer\/crop?width=200&height=200&stripmeta=true&url=https:\/\/untappd.s3.amazonaws.com\/photos\/2024_03_23\/faa3819d10ec83c0e8cdd12c557b580f_c_1366002868_raw.jpg","photo_img_md":"https:\/\/images.untp.beer\/crop?width=640&height=640&stripmeta=true&url=https:\/\/untappd.s3.amazonaws.com\/photos\/2024_03_23\/faa3819d10ec83c0e8cdd12c557b580f_c_1366002868_raw.jpg","photo_img_lg":"https:\/\/images.untp.beer\/crop?width=1280&height=1280&stripmeta=true&url=https:\/\/untappd.s3.amazonaws.com\/photos\/2024_03_23\/faa3819d10ec83c0e8cdd12c557b580f_c_1366002868_raw.jpg","photo_img_og":"https:\/\/assets.untappd.com\/photos\/2024_03_23\/faa3819d10ec83c0e8cdd12c557b580f_c_1366002868_raw.jpg"},"created_at":"Sat, 23 Mar 2024 20:02:33 +0000","checkin_id":1366002868,"beer":{"bid":5682538,"beer_name":"Off In the Woods","beer_abv":6.5,"beer_label":"https:\/\/assets.untappd.com\/site\/beer_logos\/beer-5682538_b03d4_sm.jpeg","beer_style":"IPA - American"},"brewery":{"brewery_id":531798,"brewery_name":"Wooden Axe Brewing Co","brewery_slug":"wooden-axe-brewing-co","brewery_page_url":"\/WoodenAxeBrewingCo","brewery_type":"Contract Brewery","brewery_label":"https:\/\/assets.untappd.com\/site\/brewery_logos\/brewery-531798_e625c.jpeg","country_name":"Australia","contact":{"twitter":"","facebook":"","instagram":"woodenaxebrewingco","url":"http:\/\/www.woodenaxe.beer"},"location":{"brewery_city":"","brewery_state":"","lat":0,"lng":0},"brewery_active":1},"user":{"uid":3731399,"user_name":"SchlickEtAaf","first_name":"Jonas","last_name":"Hämmer","user_avatar":"https:\/\/assets.untappd.com\/profile\/290d88a8019a328cad60b2f1d5b993eb_100x100.jpeg","is_private":0},"venue":[]},{"photo_id":533218733,"photo":{"photo_img_sm":"https:\/\/images.untp.beer\/crop?width=200&height=200&stripmeta=true&url=https:\/\/untappd.s3.amazonaws.com\/photos\/2024_03_23\/0c56abc3e804257c0e895c0f380f9f3d_c_1365695260_raw.jpg","photo_img_md":"https:\/\/images.untp.beer\/crop?width=640&height=640&stripmeta=true&url=https:\/\/untappd.s3.amazonaws.com\/photos\/2024_03_23\/0c56abc3e804257c0e895c0f380f9f3d_c_1365695260_raw.jpg","photo_img_lg":"https:\/\/images.untp.beer\/crop?width=1280&height=1280&stripmeta=true&url=https:\/\/untappd.s3.amazonaws.com\/photos\/2024_03_23\/0c56abc3e804257c0e895c0f380f9f3d_c_1365695260_raw.jpg","photo_img_og":"https:\/\/assets.untappd.com\/photos\/2024_03_23\/0c56abc3e804257c0e895c0f380f9f3d_c_1365695260_raw.jpg"},"created_at":"Sat, 23 Mar 2024 01:52:43 +0000","checkin_id":1365695260,"beer":{"bid":5487608,"beer_name":"Phase 2","beer_abv":6.5,"beer_label":"https:\/\/assets.untappd.com\/site\/beer_logos\/beer-5487608_ebe9b_sm.jpeg","beer_style":"IPA - Black \/ Cascadian Dark Ale"},"brewery":{"brewery_id":531798,"brewery_name":"Wooden Axe Brewing Co","brewery_slug":"wooden-axe-brewing-co","brewery_page_url":"\/WoodenAxeBrewingCo","brewery_type":"Contract Brewery","brewery_label":"https:\/\/assets.untappd.com\/site\/brewery_logos\/brewery-531798_e625c.jpeg","country_name":"Australia","contact":{"twitter":"","facebook":"","instagram":"woodenaxebrewingco","url":"http:\/\/www.woodenaxe.beer"},"location":{"brewery_city":"","brewery_state":"","lat":0,"lng":0},"brewery_active":1},"user":{"uid":3886355,"user_name":"jimbob_plumm","first_name":"JimBob","last_name":"Plummer","user_avatar":"https:\/\/assets.untappd.com\/profile\/9e697465661916c0a3b29cefefcb923b_100x100.jpg","is_private":0},"venue":{"venue_id":9917985,"venue_name":"Untappd at Home","venue_slug":"at-home","primary_category":null,"parent_category_id":"4e67e38e036454776db1fb3a","categories":{"count":1,"items":[{"category_key":"home_private","category_name":"Home (private)","category_id":"4bf58dd8d48988d103941735","is_primary":true}]},"location":{"venue_address":"","venue_city":"","venue_state":"NC","lat":34.2347,"lng":-77.9482},"contact":{"twitter":"","venue_url":""},"foursquare":{"foursquare_id":"5e7b4d99c91df60008e8b168","foursquare_url":"https:\/\/4sq.com\/3bDWYuq"},"venue_icon":{"sm":"https:\/\/assets.untappd.com\/venuelogos\/venue_9917985_b3a5d245_bg_64.png","md":"https:\/\/assets.untappd.com\/venuelogos\/venue_9917985_b3a5d245_bg_88.png","lg":"https:\/\/assets.untappd.com\/venuelogos\/venue_9917985_b3a5d245_bg_176.png?v=1"},"is_verified":1}},{"photo_id":533020372,"photo":{"photo_img_sm":"https:\/\/images.untp.beer\/crop?width=200&height=200&stripmeta=true&url=https:\/\/untappd.s3.amazonaws.com\/photos\/2024_03_22\/cb2eef498ce39060998d6cf6f5c33f22_c_1365340181_raw.jpg","photo_img_md":"https:\/\/images.untp.beer\/crop?width=640&height=640&stripmeta=true&url=https:\/\/untappd.s3.amazonaws.com\/photos\/2024_03_22\/cb2eef498ce39060998d6cf6f5c33f22_c_1365340181_raw.jpg","photo_img_lg":"https:\/\/images.untp.beer\/crop?width=1280&height=1280&stripmeta=true&url=https:\/\/untappd.s3.amazonaws.com\/photos\/2024_03_22\/cb2eef498ce39060998d6cf6f5c33f22_c_1365340181_raw.jpg","photo_img_og":"https:\/\/assets.untappd.com\/photos\/2024_03_22\/cb2eef498ce39060998d6cf6f5c33f22_c_1365340181_raw.jpg"},"created_at":"Fri, 22 Mar 2024 10:14:33 +0000","checkin_id":1365340181,"beer":{"bid":5682538,"beer_name":"Off In the Woods","beer_abv":6.5,"beer_label":"https:\/\/assets.untappd.com\/site\/beer_logos\/beer-5682538_b03d4_sm.jpeg","beer_style":"IPA - American"},"brewery":{"brewery_id":531798,"brewery_name":"Wooden Axe Brewing Co","brewery_slug":"wooden-axe-brewing-co","brewery_page_url":"\/WoodenAxeBrewingCo","brewery_type":"Contract Brewery","brewery_label":"https:\/\/assets.untappd.com\/site\/brewery_logos\/brewery-531798_e625c.jpeg","country_name":"Australia","contact":{"twitter":"","facebook":"","instagram":"woodenaxebrewingco","url":"http:\/\/www.woodenaxe.beer"},"location":{"brewery_city":"","brewery_state":"","lat":0,"lng":0},"brewery_active":1},"user":{"uid":2921473,"user_name":"JohnLear","first_name":"John","last_name":"Lear","user_avatar":"https:\/\/assets.untappd.com\/profile\/6bda0e6cb783f97fdf8dae38437c411f_100x100.jpg","is_private":0},"venue":{"venue_id":9917985,"venue_name":"Untappd at Home","venue_slug":"at-home","primary_category":null,"parent_category_id":"4e67e38e036454776db1fb3a","categories":{"count":1,"items":[{"category_key":"home_private","category_name":"Home (private)","category_id":"4bf58dd8d48988d103941735","is_primary":true}]},"location":{"venue_address":"","venue_city":"","venue_state":"NC","lat":34.2347,"lng":-77.9482},"contact":{"twitter":"","venue_url":""},"foursquare":{"foursquare_id":"5e7b4d99c91df60008e8b168","foursquare_url":"https:\/\/4sq.com\/3bDWYuq"},"venue_icon":{"sm":"https:\/\/assets.untappd.com\/venuelogos\/venue_9917985_b3a5d245_bg_64.png","md":"https:\/\/assets.untappd.com\/venuelogos\/venue_9917985_b3a5d245_bg_88.png","lg":"https:\/\/assets.untappd.com\/venuelogos\/venue_9917985_b3a5d245_bg_176.png?v=1"},"is_verified":1}},{"photo_id":532896932,"photo":{"photo_img_sm":"https:\/\/images.untp.beer\/crop?width=200&height=200&stripmeta=true&url=https:\/\/untappd.s3.amazonaws.com\/photos\/2024_03_21\/1059412c155f9973e79f14493c5864e9_c_1365108331_raw.jpg","photo_img_md":"https:\/\/images.untp.beer\/crop?width=640&height=640&stripmeta=true&url=https:\/\/untappd.s3.amazonaws.com\/photos\/2024_03_21\/1059412c155f9973e79f14493c5864e9_c_1365108331_raw.jpg","photo_img_lg":"https:\/\/images.untp.beer\/crop?width=1280&height=1280&stripmeta=true&url=https:\/\/untappd.s3.amazonaws.com\/photos\/2024_03_21\/1059412c155f9973e79f14493c5864e9_c_1365108331_raw.jpg","photo_img_og":"https:\/\/assets.untappd.com\/photos\/2024_03_21\/1059412c155f9973e79f14493c5864e9_c_1365108331_raw.jpg"},"created_at":"Thu, 21 Mar 2024 05:50:59 +0000","checkin_id":1365108331,"beer":{"bid":5682538,"beer_name":"Off In the Woods","beer_abv":6.5,"beer_label":"https:\/\/assets.untappd.com\/site\/beer_logos\/beer-5682538_b03d4_sm.jpeg","beer_style":"IPA - American"},"brewery":{"brewery_id":531798,"brewery_name":"Wooden Axe Brewing Co","brewery_slug":"wooden-axe-brewing-co","brewery_page_url":"\/WoodenAxeBrewingCo","brewery_type":"Contract Brewery","brewery_label":"https:\/\/assets.untappd.com\/site\/brewery_logos\/brewery-531798_e625c.jpeg","country_name":"Australia","contact":{"twitter":"","facebook":"","instagram":"woodenaxebrewingco","url":"http:\/\/www.woodenaxe.beer"},"location":{"brewery_city":"","brewery_state":"","lat":0,"lng":0},"brewery_active":1},"user":{"uid":10549720,"user_name":"aviewandabeer","first_name":"Andrew","last_name":"Frith","user_avatar":"https:\/\/assets.untappd.com\/profile\/a25735ace14c81c25f44e89c3ad97422_100x100.jpg","is_private":0},"venue":{"venue_id":9917985,"venue_name":"Untappd at Home","venue_slug":"at-home","primary_category":null,"parent_category_id":"4e67e38e036454776db1fb3a","categories":{"count":1,"items":[{"category_key":"home_private","category_name":"Home (private)","category_id":"4bf58dd8d48988d103941735","is_primary":true}]},"location":{"venue_address":"","venue_city":"","venue_state":"NC","lat":34.2347,"lng":-77.9482},"contact":{"twitter":"","venue_url":""},"foursquare":{"foursquare_id":"5e7b4d99c91df60008e8b168","foursquare_url":"https:\/\/4sq.com\/3bDWYuq"},"venue_icon":{"sm":"https:\/\/assets.untappd.com\/venuelogos\/venue_9917985_b3a5d245_bg_64.png","md":"https:\/\/assets.untappd.com\/venuelogos\/venue_9917985_b3a5d245_bg_88.png","lg":"https:\/\/assets.untappd.com\/venuelogos\/venue_9917985_b3a5d245_bg_176.png?v=1"},"is_verified":1}},{"photo_id":532809042,"photo":{"photo_img_sm":"https:\/\/images.untp.beer\/crop?width=200&height=200&stripmeta=true&url=https:\/\/untappd.s3.amazonaws.com\/photos\/2024_03_20\/24c3947034c853a64e1ccb069ffeebc1_c_1364944173_raw.jpg","photo_img_md":"https:\/\/images.untp.beer\/crop?width=640&height=640&stripmeta=true&url=https:\/\/untappd.s3.amazonaws.com\/photos\/2024_03_20\/24c3947034c853a64e1ccb069ffeebc1_c_1364944173_raw.jpg","photo_img_lg":"https:\/\/images.untp.beer\/crop?width=1280&height=1280&stripmeta=true&url=https:\/\/untappd.s3.amazonaws.com\/photos\/2024_03_20\/24c3947034c853a64e1ccb069ffeebc1_c_1364944173_raw.jpg","photo_img_og":"https:\/\/assets.untappd.com\/photos\/2024_03_20\/24c3947034c853a64e1ccb069ffeebc1_c_1364944173_raw.jpg"},"created_at":"Wed, 20 Mar 2024 09:14:25 +0000","checkin_id":1364944173,"beer":{"bid":5682538,"beer_name":"Off In the Woods","beer_abv":6.5,"beer_label":"https:\/\/assets.untappd.com\/site\/beer_logos\/beer-5682538_b03d4_sm.jpeg","beer_style":"IPA - American"},"brewery":{"brewery_id":531798,"brewery_name":"Wooden Axe Brewing Co","brewery_slug":"wooden-axe-brewing-co","brewery_page_url":"\/WoodenAxeBrewingCo","brewery_type":"Contract Brewery","brewery_label":"https:\/\/assets.untappd.com\/site\/brewery_logos\/brewery-531798_e625c.jpeg","country_name":"Australia","contact":{"twitter":"","facebook":"","instagram":"woodenaxebrewingco","url":"http:\/\/www.woodenaxe.beer"},"location":{"brewery_city":"","brewery_state":"","lat":0,"lng":0},"brewery_active":1},"user":{"uid":3276769,"user_name":"Artie69","first_name":"Paul","last_name":"Arthur","user_avatar":"https:\/\/assets.untappd.com\/profile\/b8de0c78c3d13ec1b766a69a18359bcf_100x100.jpg","is_private":0},"venue":{"venue_id":178038,"venue_name":"The Greengate Hotel","venue_slug":"the-greengate-hotel","primary_category":"Dining and Drinking","parent_category_id":"63be6904847c3692a84b9bb5","categories":{"count":1,"items":[{"category_key":"pub","category_name":"Pub","category_id":"4bf58dd8d48988d11b941735","is_primary":true}]},"location":{"venue_address":"655 Pacific Hwy","venue_city":"","venue_state":"New South Wales","lat":-33.763,"lng":151.156},"contact":{"twitter":"","venue_url":"https:\/\/www.greengatehotel.com.au"},"foursquare":{"foursquare_id":"4b0f45ebf964a5200b6123e3","foursquare_url":"http:\/\/4sq.com\/7PtIAe"},"venue_icon":{"sm":"https:\/\/ss3.4sqi.net\/img\/categories_v2\/nightlife\/pub_bg_64.png","md":"https:\/\/ss3.4sqi.net\/img\/categories_v2\/nightlife\/pub_bg_88.png","lg":"https:\/\/ss3.4sqi.net\/img\/categories_v2\/nightlife\/pub_bg_512.png"},"is_verified":0}},{"photo_id":532660102,"photo":{"photo_img_sm":"https:\/\/images.untp.beer\/crop?width=200&height=200&stripmeta=true&url=https:\/\/untappd.s3.amazonaws.com\/photos\/2024_03_18\/bd22f44da2a213eaebfc2235cd0c5ee0_c_1364662043_raw.jpg","photo_img_md":"https:\/\/images.untp.beer\/crop?width=640&height=640&stripmeta=true&url=https:\/\/untappd.s3.amazonaws.com\/photos\/2024_03_18\/bd22f44da2a213eaebfc2235cd0c5ee0_c_1364662043_raw.jpg","photo_img_lg":"https:\/\/images.untp.beer\/crop?width=1280&height=1280&stripmeta=true&url=https:\/\/untappd.s3.amazonaws.com\/photos\/2024_03_18\/bd22f44da2a213eaebfc2235cd0c5ee0_c_1364662043_raw.jpg","photo_img_og":"https:\/\/assets.untappd.com\/photos\/2024_03_18\/bd22f44da2a213eaebfc2235cd0c5ee0_c_1364662043_raw.jpg"},"created_at":"Mon, 18 Mar 2024 03:06:30 +0000","checkin_id":1364662043,"beer":{"bid":5682538,"beer_name":"Off In the Woods","beer_abv":6.5,"beer_label":"https:\/\/assets.untappd.com\/site\/beer_logos\/beer-5682538_b03d4_sm.jpeg","beer_style":"IPA - American"},"brewery":{"brewery_id":531798,"brewery_name":"Wooden Axe Brewing Co","brewery_slug":"wooden-axe-brewing-co","brewery_page_url":"\/WoodenAxeBrewingCo","brewery_type":"Contract Brewery","brewery_label":"https:\/\/assets.untappd.com\/site\/brewery_logos\/brewery-531798_e625c.jpeg","country_name":"Australia","contact":{"twitter":"","facebook":"","instagram":"woodenaxebrewingco","url":"http:\/\/www.woodenaxe.beer"},"location":{"brewery_city":"","brewery_state":"","lat":0,"lng":0},"brewery_active":1},"user":{"uid":1580450,"user_name":"Pivo_king","first_name":"Alen","last_name":"Pivo","user_avatar":"https:\/\/assets.untappd.com\/profile\/137e84f4ad15bde4679712262e367639_100x100.jpg","is_private":0},"venue":{"venue_id":656676,"venue_name":"Quarrymans Hotel","venue_slug":"quarrymans-hotel","primary_category":null,"parent_category_id":"4d4b7105d754a06376d81259","categories":{"count":3,"items":[{"category_key":"pub","category_name":"Pub","category_id":"4bf58dd8d48988d11b941735","is_primary":true},{"category_key":"beer_garden","category_name":"Beer Garden","category_id":"4bf58dd8d48988d117941735","is_primary":false},{"category_key":"rooftop_bar","category_name":"Rooftop Bar","category_id":"5f2c224bb6d05514c70440a3","is_primary":false}]},"location":{"venue_address":"214-216 Harris St","venue_city":"Pyrmont","venue_state":"NSW","lat":-33.8711,"lng":151.195},"contact":{"twitter":"@quarrymanshotel","venue_url":"https:\/\/www.quarrymans.com.au"},"foursquare":{"foursquare_id":"4b84ad0df964a520bc4031e3","foursquare_url":"http:\/\/4sq.com\/91CEew"},"venue_icon":{"sm":"https:\/\/assets.untappd.com\/venuelogos\/venue_656676_c4e11fba_bg_64.png","md":"https:\/\/assets.untappd.com\/venuelogos\/venue_656676_c4e11fba_bg_88.png","lg":"https:\/\/assets.untappd.com\/venuelogos\/venue_656676_c4e11fba_bg_176.png?v=1"},"is_verified":1}},{"photo_id":532497761,"photo":{"photo_img_sm":"https:\/\/images.untp.beer\/crop?width=200&height=200&stripmeta=true&url=https:\/\/untappd.s3.amazonaws.com\/photos\/2024_03_17\/5cb452de76629c17514dc58f543d9260_c_1364365817_raw.jpg","photo_img_md":"https:\/\/images.untp.beer\/crop?width=640&height=640&stripmeta=true&url=https:\/\/untappd.s3.amazonaws.com\/photos\/2024_03_17\/5cb452de76629c17514dc58f543d9260_c_1364365817_raw.jpg","photo_img_lg":"https:\/\/images.untp.beer\/crop?width=1280&height=1280&stripmeta=true&url=https:\/\/untappd.s3.amazonaws.com\/photos\/2024_03_17\/5cb452de76629c17514dc58f543d9260_c_1364365817_raw.jpg","photo_img_og":"https:\/\/assets.untappd.com\/photos\/2024_03_17\/5cb452de76629c17514dc58f543d9260_c_1364365817_raw.jpg"},"created_at":"Sun, 17 Mar 2024 08:42:47 +0000","checkin_id":1364365817,"beer":{"bid":5682538,"beer_name":"Off In the Woods","beer_abv":6.5,"beer_label":"https:\/\/assets.untappd.com\/site\/beer_logos\/beer-5682538_b03d4_sm.jpeg","beer_style":"IPA - American"},"brewery":{"brewery_id":531798,"brewery_name":"Wooden Axe Brewing Co","brewery_slug":"wooden-axe-brewing-co","brewery_page_url":"\/WoodenAxeBrewingCo","brewery_type":"Contract Brewery","brewery_label":"https:\/\/assets.untappd.com\/site\/brewery_logos\/brewery-531798_e625c.jpeg","country_name":"Australia","contact":{"twitter":"","facebook":"","instagram":"woodenaxebrewingco","url":"http:\/\/www.woodenaxe.beer"},"location":{"brewery_city":"","brewery_state":"","lat":0,"lng":0},"brewery_active":1},"user":{"uid":7112229,"user_name":"SuperGaz","first_name":"Garry","last_name":"Inglis","user_avatar":"https:\/\/gravatar.com\/avatar\/61c988c1b863f222366e9814f47fccaf?size=100&d=https%3A%2F%2Fassets.untappd.com%2Fsite%2Fassets%2Fimages%2Fdefault_avatar_v3_gravatar.jpg%3Fv%3D2","is_private":0},"venue":{"venue_id":9917985,"venue_name":"Untappd at Home","venue_slug":"at-home","primary_category":null,"parent_category_id":"4e67e38e036454776db1fb3a","categories":{"count":1,"items":[{"category_key":"home_private","category_name":"Home (private)","category_id":"4bf58dd8d48988d103941735","is_primary":true}]},"location":{"venue_address":"","venue_city":"","venue_state":"NC","lat":34.2347,"lng":-77.9482},"contact":{"twitter":"","venue_url":""},"foursquare":{"foursquare_id":"5e7b4d99c91df60008e8b168","foursquare_url":"https:\/\/4sq.com\/3bDWYuq"},"venue_icon":{"sm":"https:\/\/assets.untappd.com\/venuelogos\/venue_9917985_b3a5d245_bg_64.png","md":"https:\/\/assets.untappd.com\/venuelogos\/venue_9917985_b3a5d245_bg_88.png","lg":"https:\/\/assets.untappd.com\/venuelogos\/venue_9917985_b3a5d245_bg_176.png?v=1"},"is_verified":1}},{"photo_id":532495987,"photo":{"photo_img_sm":"https:\/\/images.untp.beer\/crop?width=200&height=200&stripmeta=true&url=https:\/\/untappd.s3.amazonaws.com\/photos\/2024_03_17\/12eb238807a21f8a3484f28c4545843e_c_1364362590_raw.jpg","photo_img_md":"https:\/\/images.untp.beer\/crop?width=640&height=640&stripmeta=true&url=https:\/\/untappd.s3.amazonaws.com\/photos\/2024_03_17\/12eb238807a21f8a3484f28c4545843e_c_1364362590_raw.jpg","photo_img_lg":"https:\/\/images.untp.beer\/crop?width=1280&height=1280&stripmeta=true&url=https:\/\/untappd.s3.amazonaws.com\/photos\/2024_03_17\/12eb238807a21f8a3484f28c4545843e_c_1364362590_raw.jpg","photo_img_og":"https:\/\/assets.untappd.com\/photos\/2024_03_17\/12eb238807a21f8a3484f28c4545843e_c_1364362590_raw.jpg"},"created_at":"Sun, 17 Mar 2024 07:33:31 +0000","checkin_id":1364362590,"beer":{"bid":5682538,"beer_name":"Off In the Woods","beer_abv":6.5,"beer_label":"https:\/\/assets.untappd.com\/site\/beer_logos\/beer-5682538_b03d4_sm.jpeg","beer_style":"IPA - American"},"brewery":{"brewery_id":531798,"brewery_name":"Wooden Axe Brewing Co","brewery_slug":"wooden-axe-brewing-co","brewery_page_url":"\/WoodenAxeBrewingCo","brewery_type":"Contract Brewery","brewery_label":"https:\/\/assets.untappd.com\/site\/brewery_logos\/brewery-531798_e625c.jpeg","country_name":"Australia","contact":{"twitter":"","facebook":"","instagram":"woodenaxebrewingco","url":"http:\/\/www.woodenaxe.beer"},"location":{"brewery_city":"","brewery_state":"","lat":0,"lng":0},"brewery_active":1},"user":{"uid":1059677,"user_name":"Thirstville","first_name":"Geoff","last_name":"","user_avatar":"https:\/\/assets.untappd.com\/profile\/e783d67d3235f6198aaef6839622b9a2_100x100.jpg","is_private":0},"venue":{"venue_id":656676,"venue_name":"Quarrymans Hotel","venue_slug":"quarrymans-hotel","primary_category":null,"parent_category_id":"4d4b7105d754a06376d81259","categories":{"count":3,"items":[{"category_key":"pub","category_name":"Pub","category_id":"4bf58dd8d48988d11b941735","is_primary":true},{"category_key":"beer_garden","category_name":"Beer Garden","category_id":"4bf58dd8d48988d117941735","is_primary":false},{"category_key":"rooftop_bar","category_name":"Rooftop Bar","category_id":"5f2c224bb6d05514c70440a3","is_primary":false}]},"location":{"venue_address":"214-216 Harris St","venue_city":"Pyrmont","venue_state":"NSW","lat":-33.8711,"lng":151.195},"contact":{"twitter":"@quarrymanshotel","venue_url":"https:\/\/www.quarrymans.com.au"},"foursquare":{"foursquare_id":"4b84ad0df964a520bc4031e3","foursquare_url":"http:\/\/4sq.com\/91CEew"},"venue_icon":{"sm":"https:\/\/assets.untappd.com\/venuelogos\/venue_656676_c4e11fba_bg_64.png","md":"https:\/\/assets.untappd.com\/venuelogos\/venue_656676_c4e11fba_bg_88.png","lg":"https:\/\/assets.untappd.com\/venuelogos\/venue_656676_c4e11fba_bg_176.png?v=1"},"is_verified":1}},{"photo_id":532495615,"photo":{"photo_img_sm":"https:\/\/images.untp.beer\/crop?width=200&height=200&stripmeta=true&url=https:\/\/untappd.s3.amazonaws.com\/photos\/2024_03_17\/045d3e55f23bbe47c45a24a4094abe04_c_1364361904_raw.jpg","photo_img_md":"https:\/\/images.untp.beer\/crop?width=640&height=640&stripmeta=true&url=https:\/\/untappd.s3.amazonaws.com\/photos\/2024_03_17\/045d3e55f23bbe47c45a24a4094abe04_c_1364361904_raw.jpg","photo_img_lg":"https:\/\/images.untp.beer\/crop?width=1280&height=1280&stripmeta=true&url=https:\/\/untappd.s3.amazonaws.com\/photos\/2024_03_17\/045d3e55f23bbe47c45a24a4094abe04_c_1364361904_raw.jpg","photo_img_og":"https:\/\/assets.untappd.com\/photos\/2024_03_17\/045d3e55f23bbe47c45a24a4094abe04_c_1364361904_raw.jpg"},"created_at":"Sun, 17 Mar 2024 07:16:42 +0000","checkin_id":1364361904,"beer":{"bid":5682538,"beer_name":"Off In the Woods","beer_abv":6.5,"beer_label":"https:\/\/assets.untappd.com\/site\/beer_logos\/beer-5682538_b03d4_sm.jpeg","beer_style":"IPA - American"},"brewery":{"brewery_id":531798,"brewery_name":"Wooden Axe Brewing Co","brewery_slug":"wooden-axe-brewing-co","brewery_page_url":"\/WoodenAxeBrewingCo","brewery_type":"Contract Brewery","brewery_label":"https:\/\/assets.untappd.com\/site\/brewery_logos\/brewery-531798_e625c.jpeg","country_name":"Australia","contact":{"twitter":"","facebook":"","instagram":"woodenaxebrewingco","url":"http:\/\/www.woodenaxe.beer"},"location":{"brewery_city":"","brewery_state":"","lat":0,"lng":0},"brewery_active":1},"user":{"uid":5188998,"user_name":"TheCraftyConnoisseur","first_name":"Kevin","last_name":"Smith","user_avatar":"https:\/\/assets.untappd.com\/profile\/9a4e1d53e25bc72b10bd116721155c2e_100x100.jpg","is_private":0},"venue":{"venue_id":11631197,"venue_name":"The bald & crafted","venue_slug":"the-bald-crafted","primary_category":"Dining and Drinking","parent_category_id":"63be6904847c3692a84b9bb5","categories":{"count":1,"items":[{"category_key":"bar","category_name":"Bar","category_id":"4bf58dd8d48988d116941735","is_primary":true}]},"location":{"venue_address":"11 Graceful Court","venue_city":"Cobbitty","venue_state":"NSW","lat":-33.9983,"lng":150.721},"contact":{"twitter":"","venue_url":""},"foursquare":{"foursquare_id":"634bafa2e3e7fd5052099af3","foursquare_url":"https:\/\/4sq.com\/3eyiCaN"},"venue_icon":{"sm":"https:\/\/ss3.4sqi.net\/img\/categories_v2\/nightlife\/pub_bg_64.png","md":"https:\/\/ss3.4sqi.net\/img\/categories_v2\/nightlife\/pub_bg_88.png","lg":"https:\/\/ss3.4sqi.net\/img\/categories_v2\/nightlife\/pub_bg_512.png"},"is_verified":0}},{"photo_id":532469673,"photo":{"photo_img_sm":"https:\/\/images.untp.beer\/crop?width=200&height=200&stripmeta=true&url=https:\/\/untappd.s3.amazonaws.com\/photos\/2024_03_17\/0d1311d5ecaa0e4e1105f7dffe8b3279_c_1364306278_raw.jpg","photo_img_md":"https:\/\/images.untp.beer\/crop?width=640&height=640&stripmeta=true&url=https:\/\/untappd.s3.amazonaws.com\/photos\/2024_03_17\/0d1311d5ecaa0e4e1105f7dffe8b3279_c_1364306278_raw.jpg","photo_img_lg":"https:\/\/images.untp.beer\/crop?width=1280&height=1280&stripmeta=true&url=https:\/\/untappd.s3.amazonaws.com\/photos\/2024_03_17\/0d1311d5ecaa0e4e1105f7dffe8b3279_c_1364306278_raw.jpg","photo_img_og":"https:\/\/assets.untappd.com\/photos\/2024_03_17\/0d1311d5ecaa0e4e1105f7dffe8b3279_c_1364306278_raw.jpg"},"created_at":"Sun, 17 Mar 2024 00:59:21 +0000","checkin_id":1364306278,"beer":{"bid":5682538,"beer_name":"Off In the Woods","beer_abv":6.5,"beer_label":"https:\/\/assets.untappd.com\/site\/beer_logos\/beer-5682538_b03d4_sm.jpeg","beer_style":"IPA - American"},"brewery":{"brewery_id":531798,"brewery_name":"Wooden Axe Brewing Co","brewery_slug":"wooden-axe-brewing-co","brewery_page_url":"\/WoodenAxeBrewingCo","brewery_type":"Contract Brewery","brewery_label":"https:\/\/assets.untappd.com\/site\/brewery_logos\/brewery-531798_e625c.jpeg","country_name":"Australia","contact":{"twitter":"","facebook":"","instagram":"woodenaxebrewingco","url":"http:\/\/www.woodenaxe.beer"},"location":{"brewery_city":"","brewery_state":"","lat":0,"lng":0},"brewery_active":1},"user":{"uid":2193743,"user_name":"bscampbell1972","first_name":"Günter","last_name":"","user_avatar":"https:\/\/assets.untappd.com\/profile\/4469b73c797db709909ed825f0c2d859_100x100.jpg","is_private":0},"venue":{"venue_id":656676,"venue_name":"Quarrymans Hotel","venue_slug":"quarrymans-hotel","primary_category":null,"parent_category_id":"4d4b7105d754a06376d81259","categories":{"count":3,"items":[{"category_key":"pub","category_name":"Pub","category_id":"4bf58dd8d48988d11b941735","is_primary":true},{"category_key":"beer_garden","category_name":"Beer Garden","category_id":"4bf58dd8d48988d117941735","is_primary":false},{"category_key":"rooftop_bar","category_name":"Rooftop Bar","category_id":"5f2c224bb6d05514c70440a3","is_primary":false}]},"location":{"venue_address":"214-216 Harris St","venue_city":"Pyrmont","venue_state":"NSW","lat":-33.8711,"lng":151.195},"contact":{"twitter":"@quarrymanshotel","venue_url":"https:\/\/www.quarrymans.com.au"},"foursquare":{"foursquare_id":"4b84ad0df964a520bc4031e3","foursquare_url":"http:\/\/4sq.com\/91CEew"},"venue_icon":{"sm":"https:\/\/assets.untappd.com\/venuelogos\/venue_656676_c4e11fba_bg_64.png","md":"https:\/\/assets.untappd.com\/venuelogos\/venue_656676_c4e11fba_bg_88.png","lg":"https:\/\/assets.untappd.com\/venuelogos\/venue_656676_c4e11fba_bg_176.png?v=1"},"is_verified":1}},{"photo_id":532215255,"photo":{"photo_img_sm":"https:\/\/images.untp.beer\/crop?width=200&height=200&stripmeta=true&url=https:\/\/untappd.s3.amazonaws.com\/photos\/2024_03_16\/b859a33f45e7ba2eb0061ea667f5ffab_c_1363845066_raw.jpg","photo_img_md":"https:\/\/images.untp.beer\/crop?width=640&height=640&stripmeta=true&url=https:\/\/untappd.s3.amazonaws.com\/photos\/2024_03_16\/b859a33f45e7ba2eb0061ea667f5ffab_c_1363845066_raw.jpg","photo_img_lg":"https:\/\/images.untp.beer\/crop?width=1280&height=1280&stripmeta=true&url=https:\/\/untappd.s3.amazonaws.com\/photos\/2024_03_16\/b859a33f45e7ba2eb0061ea667f5ffab_c_1363845066_raw.jpg","photo_img_og":"https:\/\/assets.untappd.com\/photos\/2024_03_16\/b859a33f45e7ba2eb0061ea667f5ffab_c_1363845066_raw.jpg"},"created_at":"Sat, 16 Mar 2024 09:26:33 +0000","checkin_id":1363845066,"beer":{"bid":5682538,"beer_name":"Off In the Woods","beer_abv":6.5,"beer_label":"https:\/\/assets.untappd.com\/site\/beer_logos\/beer-5682538_b03d4_sm.jpeg","beer_style":"IPA - American"},"brewery":{"brewery_id":531798,"brewery_name":"Wooden Axe Brewing Co","brewery_slug":"wooden-axe-brewing-co","brewery_page_url":"\/WoodenAxeBrewingCo","brewery_type":"Contract Brewery","brewery_label":"https:\/\/assets.untappd.com\/site\/brewery_logos\/brewery-531798_e625c.jpeg","country_name":"Australia","contact":{"twitter":"","facebook":"","instagram":"woodenaxebrewingco","url":"http:\/\/www.woodenaxe.beer"},"location":{"brewery_city":"","brewery_state":"","lat":0,"lng":0},"brewery_active":1},"user":{"uid":2411696,"user_name":"Donaldus","first_name":"Michael","last_name":"Staats","user_avatar":"https:\/\/assets.untappd.com\/profile\/0eedf9fec12d8742610369d4224ab993_100x100.jpeg","is_private":0},"venue":{"venue_id":9917985,"venue_name":"Untappd at Home","venue_slug":"at-home","primary_category":null,"parent_category_id":"4e67e38e036454776db1fb3a","categories":{"count":1,"items":[{"category_key":"home_private","category_name":"Home (private)","category_id":"4bf58dd8d48988d103941735","is_primary":true}]},"location":{"venue_address":"","venue_city":"","venue_state":"NC","lat":34.2347,"lng":-77.9482},"contact":{"twitter":"","venue_url":""},"foursquare":{"foursquare_id":"5e7b4d99c91df60008e8b168","foursquare_url":"https:\/\/4sq.com\/3bDWYuq"},"venue_icon":{"sm":"https:\/\/assets.untappd.com\/venuelogos\/venue_9917985_b3a5d245_bg_64.png","md":"https:\/\/assets.untappd.com\/venuelogos\/venue_9917985_b3a5d245_bg_88.png","lg":"https:\/\/assets.untappd.com\/venuelogos\/venue_9917985_b3a5d245_bg_176.png?v=1"},"is_verified":1}},{"photo_id":532214187,"photo":{"photo_img_sm":"https:\/\/images.untp.beer\/crop?width=200&height=200&stripmeta=true&url=https:\/\/untappd.s3.amazonaws.com\/photos\/2024_03_16\/f835f2212ad71894a1b7b2feb9279743_c_1363843132_raw.jpg","photo_img_md":"https:\/\/images.untp.beer\/crop?width=640&height=640&stripmeta=true&url=https:\/\/untappd.s3.amazonaws.com\/photos\/2024_03_16\/f835f2212ad71894a1b7b2feb9279743_c_1363843132_raw.jpg","photo_img_lg":"https:\/\/images.untp.beer\/crop?width=1280&height=1280&stripmeta=true&url=https:\/\/untappd.s3.amazonaws.com\/photos\/2024_03_16\/f835f2212ad71894a1b7b2feb9279743_c_1363843132_raw.jpg","photo_img_og":"https:\/\/assets.untappd.com\/photos\/2024_03_16\/f835f2212ad71894a1b7b2feb9279743_c_1363843132_raw.jpg"},"created_at":"Sat, 16 Mar 2024 08:53:11 +0000","checkin_id":1363843132,"beer":{"bid":5682538,"beer_name":"Off In the Woods","beer_abv":6.5,"beer_label":"https:\/\/assets.untappd.com\/site\/beer_logos\/beer-5682538_b03d4_sm.jpeg","beer_style":"IPA - American"},"brewery":{"brewery_id":531798,"brewery_name":"Wooden Axe Brewing Co","brewery_slug":"wooden-axe-brewing-co","brewery_page_url":"\/WoodenAxeBrewingCo","brewery_type":"Contract Brewery","brewery_label":"https:\/\/assets.untappd.com\/site\/brewery_logos\/brewery-531798_e625c.jpeg","country_name":"Australia","contact":{"twitter":"","facebook":"","instagram":"woodenaxebrewingco","url":"http:\/\/www.woodenaxe.beer"},"location":{"brewery_city":"","brewery_state":"","lat":0,"lng":0},"brewery_active":1},"user":{"uid":1755427,"user_name":"satanietzsche","first_name":"Steven","last_name":"Dero","user_avatar":"https:\/\/assets.untappd.com\/profile\/3f0cf9bd90873c48881770f439d352ed_100x100.jpg","is_private":0},"venue":{"venue_id":591913,"venue_name":"Clifton Hill","venue_slug":"clifton-hill","primary_category":"Landmarks and Outdoors","parent_category_id":"4d4b7105d754a06377d81259","categories":{"count":1,"items":[{"category_key":"neighborhood","category_name":"Neighborhood","category_id":"4f2a25ac4b909258e854f55f","is_primary":true}]},"location":{"venue_address":"","venue_city":"Clifton Hill","venue_state":"VIC","lat":-37.7888,"lng":144.994},"contact":{"twitter":"@yarracouncil","venue_url":""},"foursquare":{"foursquare_id":"4d8e7cf7d4ec8cfac5457589","foursquare_url":"http:\/\/4sq.com\/et8D3q"},"venue_icon":{"sm":"https:\/\/ss3.4sqi.net\/img\/categories_v2\/parks_outdoors\/neighborhood_bg_64.png","md":"https:\/\/ss3.4sqi.net\/img\/categories_v2\/parks_outdoors\/neighborhood_bg_88.png","lg":"https:\/\/ss3.4sqi.net\/img\/categories_v2\/parks_outdoors\/neighborhood_bg_512.png"},"is_verified":0}}]},"checkins":{"count":15,"items":[{"checkin_id":1367342532,"created_at":"Fri, 29 Mar 2024 06:16:48 +0000","checkin_comment":"","rating_score":4.25,"user":{"uid":23556,"user_name":"mablack","first_name":"Michael","last_name":"Black","location":"Bentleigh, Victoria","url":"","is_supporter":0,"bio":"","relationship":null,"user_avatar":"https:\/\/gravatar.com\/avatar\/0079a9ec10e827340ce9b26c933dcb4a?size=100&d=https%3A%2F%2Fassets.untappd.com%2Fsite%2Fassets%2Fimages%2Fdefault_avatar_v3_gravatar.jpg%3Fv%3D2","is_private":0,"public_toasts":1},"beer":{"bid":5682538,"beer_name":"Off In the Woods","beer_label":"https:\/\/assets.untappd.com\/site\/beer_logos\/beer-5682538_b03d4_sm.jpeg","beer_abv":6.5,"beer_ibu":60,"beer_slug":"wooden-axe-brewing-co-off-in-the-woods","beer_description":"Introducing our West Coast IPA, generously double dry-hopped with Azacca, Idaho 7 & Strata hops. This hop trifecta delivers a burst of tropical fruit, citrus, and dank pine notes. With a crisp, clean malt backbone and a refreshing bitterness, this beer is a vibrant homage to the Pacific-Northwest's hop-rich landscapes. Dank, Piney & Resinous... Can't beat it!","beer_style":"IPA - American","has_had":false,"beer_active":1},"brewery":{"brewery_id":531798,"brewery_name":"Wooden Axe Brewing Co","brewery_slug":"wooden-axe-brewing-co","brewery_page_url":"\/WoodenAxeBrewingCo","brewery_label":"https:\/\/assets.untappd.com\/site\/brewery_logos\/brewery-531798_e625c.jpeg","country_name":"Australia","contact":{"twitter":"","facebook":"","url":"http:\/\/www.woodenaxe.beer"},"location":{"brewery_city":"","brewery_state":"","lat":0,"lng":0},"brewery_active":1},"venue":{"venue_id":9917985,"venue_name":"Untappd at Home","venue_slug":"at-home","primary_category_key":null,"primary_category":null,"parent_category_id":"4e67e38e036454776db1fb3a","categories":{"count":1,"items":[{"category_key":"home_private","category_name":"Home (private)","category_id":"4bf58dd8d48988d103941735","is_primary":true}]},"location":{"venue_address":"","venue_city":"","venue_state":"NC","venue_country":"United States","lat":34.2346611,"lng":-77.9482117},"contact":{"twitter":"","venue_url":""},"foursquare":{"foursquare_id":"5e7b4d99c91df60008e8b168","foursquare_url":"https:\/\/4sq.com\/3bDWYuq"},"venue_icon":{"sm":"https:\/\/assets.untappd.com\/venuelogos\/venue_9917985_b3a5d245_bg_64.png","md":"https:\/\/assets.untappd.com\/venuelogos\/venue_9917985_b3a5d245_bg_88.png","lg":"https:\/\/assets.untappd.com\/venuelogos\/venue_9917985_b3a5d245_bg_176.png?v=1"},"is_verified":true},"comments":{"total_count":0,"count":0,"items":[]},"toasts":{"total_count":0,"count":0,"auth_toast":false,"items":[]},"media":{"count":0,"items":[]},"source":{"app_name":"Untappd for iPhone - (V2)","app_website":"http:\/\/untpd.it\/iphoneapp"},"badges":{"retro_status":false,"count":1,"items":[{"badge_id":243541,"user_badge_id":1189795848,"badge_name":"Brewery Pioneer (Level 46)","badge_description":"There's beer in them thar hills! You're setting off on your journey through the world of beer, but be sure to take a little time to get to know each brewery as you go. That's a beer from 230 different breweries. Try 5 more for Level 47!","created_at":"Fri, 29 Mar 2024 06:16:49 +0000","badge_image":{"sm":"https:\/\/assets.untappd.com\/badges\/bdg_brewery_prioneer_sm.jpg","md":"https:\/\/assets.untappd.com\/badges\/bdg_brewery_prioneer_sm.jpg","lg":"https:\/\/assets.untappd.com\/badges\/bdg_brewery_prioneer_sm.jpg"}}]}},{"checkin_id":1367065576,"created_at":"Thu, 28 Mar 2024 12:08:06 +0000","checkin_comment":"","rating_score":2,"user":{"uid":2476119,"user_name":"MickMackay","first_name":"Michael","last_name":"Mackay","location":"","url":"","is_supporter":0,"bio":"","relationship":null,"user_avatar":"https:\/\/gravatar.com\/avatar\/71c93ea59eae1b7a57e556a2b06c0f60?size=100&d=https%3A%2F%2Fassets.untappd.com%2Fsite%2Fassets%2Fimages%2Fdefault_avatar_v3_gravatar.jpg%3Fv%3D2","is_private":0,"public_toasts":1},"beer":{"bid":5682538,"beer_name":"Off In the Woods","beer_label":"https:\/\/assets.untappd.com\/site\/beer_logos\/beer-5682538_b03d4_sm.jpeg","beer_abv":6.5,"beer_ibu":60,"beer_slug":"wooden-axe-brewing-co-off-in-the-woods","beer_description":"Introducing our West Coast IPA, generously double dry-hopped with Azacca, Idaho 7 & Strata hops. This hop trifecta delivers a burst of tropical fruit, citrus, and dank pine notes. With a crisp, clean malt backbone and a refreshing bitterness, this beer is a vibrant homage to the Pacific-Northwest's hop-rich landscapes. Dank, Piney & Resinous... Can't beat it!","beer_style":"IPA - American","has_had":false,"beer_active":1},"brewery":{"brewery_id":531798,"brewery_name":"Wooden Axe Brewing Co","brewery_slug":"wooden-axe-brewing-co","brewery_page_url":"\/WoodenAxeBrewingCo","brewery_label":"https:\/\/assets.untappd.com\/site\/brewery_logos\/brewery-531798_e625c.jpeg","country_name":"Australia","contact":{"twitter":"","facebook":"","url":"http:\/\/www.woodenaxe.beer"},"location":{"brewery_city":"","brewery_state":"","lat":0,"lng":0},"brewery_active":1},"venue":{"venue_id":9917985,"venue_name":"Untappd at Home","venue_slug":"at-home","primary_category_key":null,"primary_category":null,"parent_category_id":"4e67e38e036454776db1fb3a","categories":{"count":1,"items":[{"category_key":"home_private","category_name":"Home (private)","category_id":"4bf58dd8d48988d103941735","is_primary":true}]},"location":{"venue_address":"","venue_city":"","venue_state":"NC","venue_country":"United States","lat":34.2346611,"lng":-77.9482117},"contact":{"twitter":"","venue_url":""},"foursquare":{"foursquare_id":"5e7b4d99c91df60008e8b168","foursquare_url":"https:\/\/4sq.com\/3bDWYuq"},"venue_icon":{"sm":"https:\/\/assets.untappd.com\/venuelogos\/venue_9917985_b3a5d245_bg_64.png","md":"https:\/\/assets.untappd.com\/venuelogos\/venue_9917985_b3a5d245_bg_88.png","lg":"https:\/\/assets.untappd.com\/venuelogos\/venue_9917985_b3a5d245_bg_176.png?v=1"},"is_verified":true},"comments":{"total_count":0,"count":0,"items":[]},"toasts":{"total_count":0,"count":0,"auth_toast":false,"items":[]},"media":{"count":0,"items":[]},"source":{"app_name":"Untappd for iPhone - (V4)","app_website":"http:\/\/untpd.it\/iphoneapp"},"badges":{"count":0,"items":[]}},{"checkin_id":1366857389,"created_at":"Wed, 27 Mar 2024 07:51:55 +0000","checkin_comment":"","rating_score":3,"user":{"uid":10040944,"user_name":"Malsop","first_name":"Matthew","last_name":"Alsop","location":"","url":"","is_supporter":0,"bio":"","relationship":null,"user_avatar":"https:\/\/gravatar.com\/avatar\/ce749539232060a5f6c455daa759cc73?size=100&d=https%3A%2F%2Fassets.untappd.com%2Fsite%2Fassets%2Fimages%2Fdefault_avatar_v3_gravatar.jpg%3Fv%3D2","is_private":0,"public_toasts":1},"beer":{"bid":5682538,"beer_name":"Off In the Woods","beer_label":"https:\/\/assets.untappd.com\/site\/beer_logos\/beer-5682538_b03d4_sm.jpeg","beer_abv":6.5,"beer_ibu":60,"beer_slug":"wooden-axe-brewing-co-off-in-the-woods","beer_description":"Introducing our West Coast IPA, generously double dry-hopped with Azacca, Idaho 7 & Strata hops. This hop trifecta delivers a burst of tropical fruit, citrus, and dank pine notes. With a crisp, clean malt backbone and a refreshing bitterness, this beer is a vibrant homage to the Pacific-Northwest's hop-rich landscapes. Dank, Piney & Resinous... Can't beat it!","beer_style":"IPA - American","has_had":false,"beer_active":1},"brewery":{"brewery_id":531798,"brewery_name":"Wooden Axe Brewing Co","brewery_slug":"wooden-axe-brewing-co","brewery_page_url":"\/WoodenAxeBrewingCo","brewery_label":"https:\/\/assets.untappd.com\/site\/brewery_logos\/brewery-531798_e625c.jpeg","country_name":"Australia","contact":{"twitter":"","facebook":"","url":"http:\/\/www.woodenaxe.beer"},"location":{"brewery_city":"","brewery_state":"","lat":0,"lng":0},"brewery_active":1},"venue":{"venue_id":9917985,"venue_name":"Untappd at Home","venue_slug":"at-home","primary_category_key":null,"primary_category":null,"parent_category_id":"4e67e38e036454776db1fb3a","categories":{"count":1,"items":[{"category_key":"home_private","category_name":"Home (private)","category_id":"4bf58dd8d48988d103941735","is_primary":true}]},"location":{"venue_address":"","venue_city":"","venue_state":"NC","venue_country":"United States","lat":34.2346611,"lng":-77.9482117},"contact":{"twitter":"","venue_url":""},"foursquare":{"foursquare_id":"5e7b4d99c91df60008e8b168","foursquare_url":"https:\/\/4sq.com\/3bDWYuq"},"venue_icon":{"sm":"https:\/\/assets.untappd.com\/venuelogos\/venue_9917985_b3a5d245_bg_64.png","md":"https:\/\/assets.untappd.com\/venuelogos\/venue_9917985_b3a5d245_bg_88.png","lg":"https:\/\/assets.untappd.com\/venuelogos\/venue_9917985_b3a5d245_bg_176.png?v=1"},"is_verified":true},"comments":{"total_count":0,"count":0,"items":[]},"toasts":{"total_count":0,"count":0,"auth_toast":false,"items":[]},"media":{"count":0,"items":[]},"source":{"app_name":"Untappd for Android - (V2)","app_website":"http:\/\/untpd.it\/androidapp"},"badges":{"count":0,"items":[]}},{"checkin_id":1366687508,"created_at":"Tue, 26 Mar 2024 06:40:35 +0000","checkin_comment":"","rating_score":3.75,"user":{"uid":4091968,"user_name":"telfitz","first_name":"Terry","last_name":"Fitzgerald","location":"Sydney, NSW","url":"","is_supporter":0,"bio":"","relationship":null,"user_avatar":"https:\/\/gravatar.com\/avatar\/4b1adbae76434c3a270469effd6bf6cb?size=100&d=https%3A%2F%2Fassets.untappd.com%2Fsite%2Fassets%2Fimages%2Fdefault_avatar_v3_gravatar.jpg%3Fv%3D2","is_private":0,"public_toasts":1},"beer":{"bid":5682538,"beer_name":"Off In the Woods","beer_label":"https:\/\/assets.untappd.com\/site\/beer_logos\/beer-5682538_b03d4_sm.jpeg","beer_abv":6.5,"beer_ibu":60,"beer_slug":"wooden-axe-brewing-co-off-in-the-woods","beer_description":"Introducing our West Coast IPA, generously double dry-hopped with Azacca, Idaho 7 & Strata hops. This hop trifecta delivers a burst of tropical fruit, citrus, and dank pine notes. With a crisp, clean malt backbone and a refreshing bitterness, this beer is a vibrant homage to the Pacific-Northwest's hop-rich landscapes. Dank, Piney & Resinous... Can't beat it!","beer_style":"IPA - American","has_had":false,"beer_active":1},"brewery":{"brewery_id":531798,"brewery_name":"Wooden Axe Brewing Co","brewery_slug":"wooden-axe-brewing-co","brewery_page_url":"\/WoodenAxeBrewingCo","brewery_label":"https:\/\/assets.untappd.com\/site\/brewery_logos\/brewery-531798_e625c.jpeg","country_name":"Australia","contact":{"twitter":"","facebook":"","url":"http:\/\/www.woodenaxe.beer"},"location":{"brewery_city":"","brewery_state":"","lat":0,"lng":0},"brewery_active":1},"venue":{"venue_id":9917985,"venue_name":"Untappd at Home","venue_slug":"at-home","primary_category_key":null,"primary_category":null,"parent_category_id":"4e67e38e036454776db1fb3a","categories":{"count":1,"items":[{"category_key":"home_private","category_name":"Home (private)","category_id":"4bf58dd8d48988d103941735","is_primary":true}]},"location":{"venue_address":"","venue_city":"","venue_state":"NC","venue_country":"United States","lat":34.2346611,"lng":-77.9482117},"contact":{"twitter":"","venue_url":""},"foursquare":{"foursquare_id":"5e7b4d99c91df60008e8b168","foursquare_url":"https:\/\/4sq.com\/3bDWYuq"},"venue_icon":{"sm":"https:\/\/assets.untappd.com\/venuelogos\/venue_9917985_b3a5d245_bg_64.png","md":"https:\/\/assets.untappd.com\/venuelogos\/venue_9917985_b3a5d245_bg_88.png","lg":"https:\/\/assets.untappd.com\/venuelogos\/venue_9917985_b3a5d245_bg_176.png?v=1"},"is_verified":true},"comments":{"total_count":0,"count":0,"items":[]},"toasts":{"total_count":0,"count":0,"auth_toast":false,"items":[]},"media":{"count":0,"items":[]},"source":{"app_name":"Untappd for Android - (V4)","app_website":"http:\/\/untpd.it\/androidapp"},"badges":{"count":0,"items":[]}},{"checkin_id":1366544633,"created_at":"Mon, 25 Mar 2024 08:11:33 +0000","checkin_comment":"Still malty. Aroma doesn’t linger. Balanced with nice bitterness. Azzaca, Idaho7 and Strata hops. Not singing citrus.","rating_score":3.25,"user":{"uid":8777114,"user_name":"john_vendel_8761","first_name":"John","last_name":"Vendel","location":"","url":"","is_supporter":0,"bio":"","relationship":null,"user_avatar":"https:\/\/assets.untappd.com\/profile\/8b5d580270d7f81c41e92fc3f124455d_100x100.jpg","is_private":0,"public_toasts":1},"beer":{"bid":5682538,"beer_name":"Off In the Woods","beer_label":"https:\/\/assets.untappd.com\/site\/beer_logos\/beer-5682538_b03d4_sm.jpeg","beer_abv":6.5,"beer_ibu":60,"beer_slug":"wooden-axe-brewing-co-off-in-the-woods","beer_description":"Introducing our West Coast IPA, generously double dry-hopped with Azacca, Idaho 7 & Strata hops. This hop trifecta delivers a burst of tropical fruit, citrus, and dank pine notes. With a crisp, clean malt backbone and a refreshing bitterness, this beer is a vibrant homage to the Pacific-Northwest's hop-rich landscapes. Dank, Piney & Resinous... Can't beat it!","beer_style":"IPA - American","has_had":false,"beer_active":1},"brewery":{"brewery_id":531798,"brewery_name":"Wooden Axe Brewing Co","brewery_slug":"wooden-axe-brewing-co","brewery_page_url":"\/WoodenAxeBrewingCo","brewery_label":"https:\/\/assets.untappd.com\/site\/brewery_logos\/brewery-531798_e625c.jpeg","country_name":"Australia","contact":{"twitter":"","facebook":"","url":"http:\/\/www.woodenaxe.beer"},"location":{"brewery_city":"","brewery_state":"","lat":0,"lng":0},"brewery_active":1},"venue":{"venue_id":9917985,"venue_name":"Untappd at Home","venue_slug":"at-home","primary_category_key":null,"primary_category":null,"parent_category_id":"4e67e38e036454776db1fb3a","categories":{"count":1,"items":[{"category_key":"home_private","category_name":"Home (private)","category_id":"4bf58dd8d48988d103941735","is_primary":true}]},"location":{"venue_address":"","venue_city":"","venue_state":"NC","venue_country":"United States","lat":34.2346611,"lng":-77.9482117},"contact":{"twitter":"","venue_url":""},"foursquare":{"foursquare_id":"5e7b4d99c91df60008e8b168","foursquare_url":"https:\/\/4sq.com\/3bDWYuq"},"venue_icon":{"sm":"https:\/\/assets.untappd.com\/venuelogos\/venue_9917985_b3a5d245_bg_64.png","md":"https:\/\/assets.untappd.com\/venuelogos\/venue_9917985_b3a5d245_bg_88.png","lg":"https:\/\/assets.untappd.com\/venuelogos\/venue_9917985_b3a5d245_bg_176.png?v=1"},"is_verified":true},"comments":{"total_count":0,"count":0,"items":[]},"toasts":{"total_count":2,"count":2,"auth_toast":null,"items":[{"uid":8134533,"user":{"uid":8134533,"user_name":"Pullos","first_name":"Matt","last_name":"Pullen","bio":"","location":"","relationship":"none","user_avatar":"https:\/\/assets.untappd.com\/profile\/2fdd31f38cbf9e926862bb2fe5a3f421_100x100.jpg","account_type":"user","venue_details":[],"brewery_details":[]},"like_id":1485010432,"like_owner":false,"created_at":"Wed, 27 Mar 2024 07:56:39 +0000"},{"uid":10191865,"user":{"uid":10191865,"user_name":"WoodenAxeBrewingCo","first_name":"Wooden Axe Brewing Co","last_name":"","bio":"","location":"","relationship":"none","user_avatar":"https:\/\/assets.untappd.com\/site\/brewery_logos\/brewery-531798_e625c.jpeg","account_type":"brewery","venue_details":[],"brewery_details":{"brewery_id":531798},"user_link":"https:\/\/untappd.com\/brewery\/531798"},"like_id":1484521815,"like_owner":false,"created_at":"Mon, 25 Mar 2024 10:18:29 +0000"}]},"media":{"count":1,"items":[{"photo_id":533678753,"photo":{"photo_img_sm":"https:\/\/images.untp.beer\/crop?width=200&height=200&stripmeta=true&url=https:\/\/untappd.s3.amazonaws.com\/photos\/2024_03_25\/ad532c3192b7391f8ac51fd9b7449ae8_c_1366544633_raw.jpg","photo_img_md":"https:\/\/images.untp.beer\/crop?width=640&height=640&stripmeta=true&url=https:\/\/untappd.s3.amazonaws.com\/photos\/2024_03_25\/ad532c3192b7391f8ac51fd9b7449ae8_c_1366544633_raw.jpg","photo_img_lg":"https:\/\/images.untp.beer\/crop?width=1280&height=1280&stripmeta=true&url=https:\/\/untappd.s3.amazonaws.com\/photos\/2024_03_25\/ad532c3192b7391f8ac51fd9b7449ae8_c_1366544633_raw.jpg","photo_img_og":"https:\/\/assets.untappd.com\/photos\/2024_03_25\/ad532c3192b7391f8ac51fd9b7449ae8_c_1366544633_raw.jpg"}}]},"source":{"app_name":"Untappd for iPhone - (V4)","app_website":"http:\/\/untpd.it\/iphoneapp"},"badges":{"count":0,"items":[]}},{"checkin_id":1366268335,"created_at":"Sun, 24 Mar 2024 11:39:28 +0000","checkin_comment":"Big pine hit, with more punch from strata. Goes better in a piney style than in citrusy beers!","rating_score":3.75,"user":{"uid":928722,"user_name":"dr_keg","first_name":"Tom","last_name":"Wellings","location":"","url":"","is_supporter":0,"bio":"","relationship":null,"user_avatar":"https:\/\/assets.untappd.com\/profile\/d7ba47ebe4cc9bdb539c78ff9aab8ec4_100x100.jpg","is_private":0,"public_toasts":1},"beer":{"bid":5682538,"beer_name":"Off In the Woods","beer_label":"https:\/\/assets.untappd.com\/site\/beer_logos\/beer-5682538_b03d4_sm.jpeg","beer_abv":6.5,"beer_ibu":60,"beer_slug":"wooden-axe-brewing-co-off-in-the-woods","beer_description":"Introducing our West Coast IPA, generously double dry-hopped with Azacca, Idaho 7 & Strata hops. This hop trifecta delivers a burst of tropical fruit, citrus, and dank pine notes. With a crisp, clean malt backbone and a refreshing bitterness, this beer is a vibrant homage to the Pacific-Northwest's hop-rich landscapes. Dank, Piney & Resinous... Can't beat it!","beer_style":"IPA - American","has_had":false,"beer_active":1},"brewery":{"brewery_id":531798,"brewery_name":"Wooden Axe Brewing Co","brewery_slug":"wooden-axe-brewing-co","brewery_page_url":"\/WoodenAxeBrewingCo","brewery_label":"https:\/\/assets.untappd.com\/site\/brewery_logos\/brewery-531798_e625c.jpeg","country_name":"Australia","contact":{"twitter":"","facebook":"","url":"http:\/\/www.woodenaxe.beer"},"location":{"brewery_city":"","brewery_state":"","lat":0,"lng":0},"brewery_active":1},"venue":{"venue_id":9917985,"venue_name":"Untappd at Home","venue_slug":"at-home","primary_category_key":null,"primary_category":null,"parent_category_id":"4e67e38e036454776db1fb3a","categories":{"count":1,"items":[{"category_key":"home_private","category_name":"Home (private)","category_id":"4bf58dd8d48988d103941735","is_primary":true}]},"location":{"venue_address":"","venue_city":"","venue_state":"NC","venue_country":"United States","lat":34.2346611,"lng":-77.9482117},"contact":{"twitter":"","venue_url":""},"foursquare":{"foursquare_id":"5e7b4d99c91df60008e8b168","foursquare_url":"https:\/\/4sq.com\/3bDWYuq"},"venue_icon":{"sm":"https:\/\/assets.untappd.com\/venuelogos\/venue_9917985_b3a5d245_bg_64.png","md":"https:\/\/assets.untappd.com\/venuelogos\/venue_9917985_b3a5d245_bg_88.png","lg":"https:\/\/assets.untappd.com\/venuelogos\/venue_9917985_b3a5d245_bg_176.png?v=1"},"is_verified":true},"comments":{"total_count":0,"count":0,"items":[]},"toasts":{"total_count":1,"count":1,"auth_toast":null,"items":[{"uid":10191865,"user":{"uid":10191865,"user_name":"WoodenAxeBrewingCo","first_name":"Wooden Axe Brewing Co","last_name":"","bio":"","location":"","relationship":"none","user_avatar":"https:\/\/assets.untappd.com\/site\/brewery_logos\/brewery-531798_e625c.jpeg","account_type":"brewery","venue_details":[],"brewery_details":{"brewery_id":531798},"user_link":"https:\/\/untappd.com\/brewery\/531798"},"like_id":1484521845,"like_owner":false,"created_at":"Mon, 25 Mar 2024 10:18:40 +0000"}]},"media":{"count":1,"items":[{"photo_id":533528579,"photo":{"photo_img_sm":"https:\/\/images.untp.beer\/crop?width=200&height=200&stripmeta=true&url=https:\/\/untappd.s3.amazonaws.com\/photos\/2024_03_24\/ed804361191d3d81a14b02b1449d865d_c_1366268335_raw.jpg","photo_img_md":"https:\/\/images.untp.beer\/crop?width=640&height=640&stripmeta=true&url=https:\/\/untappd.s3.amazonaws.com\/photos\/2024_03_24\/ed804361191d3d81a14b02b1449d865d_c_1366268335_raw.jpg","photo_img_lg":"https:\/\/images.untp.beer\/crop?width=1280&height=1280&stripmeta=true&url=https:\/\/untappd.s3.amazonaws.com\/photos\/2024_03_24\/ed804361191d3d81a14b02b1449d865d_c_1366268335_raw.jpg","photo_img_og":"https:\/\/assets.untappd.com\/photos\/2024_03_24\/ed804361191d3d81a14b02b1449d865d_c_1366268335_raw.jpg"}}]},"source":{"app_name":"Untappd for iPhone - (V4)","app_website":"http:\/\/untpd.it\/iphoneapp"},"badges":{"count":0,"items":[]}},{"checkin_id":1366250679,"created_at":"Sun, 24 Mar 2024 06:17:33 +0000","checkin_comment":"","rating_score":3.5,"user":{"uid":1447073,"user_name":"Mattbell1","first_name":"Matt","last_name":"Bell","location":"","url":"","is_supporter":0,"bio":"","relationship":null,"user_avatar":"https:\/\/assets.untappd.com\/profile\/f47214b840cdcc2782452bbc956a7dfe_100x100.jpg","is_private":0,"public_toasts":1},"beer":{"bid":5682538,"beer_name":"Off In the Woods","beer_label":"https:\/\/assets.untappd.com\/site\/beer_logos\/beer-5682538_b03d4_sm.jpeg","beer_abv":6.5,"beer_ibu":60,"beer_slug":"wooden-axe-brewing-co-off-in-the-woods","beer_description":"Introducing our West Coast IPA, generously double dry-hopped with Azacca, Idaho 7 & Strata hops. This hop trifecta delivers a burst of tropical fruit, citrus, and dank pine notes. With a crisp, clean malt backbone and a refreshing bitterness, this beer is a vibrant homage to the Pacific-Northwest's hop-rich landscapes. Dank, Piney & Resinous... Can't beat it!","beer_style":"IPA - American","has_had":false,"beer_active":1},"brewery":{"brewery_id":531798,"brewery_name":"Wooden Axe Brewing Co","brewery_slug":"wooden-axe-brewing-co","brewery_page_url":"\/WoodenAxeBrewingCo","brewery_label":"https:\/\/assets.untappd.com\/site\/brewery_logos\/brewery-531798_e625c.jpeg","country_name":"Australia","contact":{"twitter":"","facebook":"","url":"http:\/\/www.woodenaxe.beer"},"location":{"brewery_city":"","brewery_state":"","lat":0,"lng":0},"brewery_active":1},"venue":{"venue_id":178038,"venue_name":"The Greengate Hotel","venue_slug":"the-greengate-hotel","primary_category_key":"Dining and Drinking","primary_category":"Dining and Drinking","parent_category_id":"63be6904847c3692a84b9bb5","categories":{"count":1,"items":[{"category_key":"pub","category_name":"Pub","category_id":"4bf58dd8d48988d11b941735","is_primary":true}]},"location":{"venue_address":"655 Pacific Hwy","venue_city":"","venue_state":"New South Wales","venue_country":"Australia","lat":-33.7630005,"lng":151.1556244},"contact":{"twitter":"","venue_url":"https:\/\/www.greengatehotel.com.au"},"foursquare":{"foursquare_id":"4b0f45ebf964a5200b6123e3","foursquare_url":"http:\/\/4sq.com\/7PtIAe"},"venue_icon":{"sm":"https:\/\/ss3.4sqi.net\/img\/categories_v2\/nightlife\/pub_bg_64.png","md":"https:\/\/ss3.4sqi.net\/img\/categories_v2\/nightlife\/pub_bg_88.png","lg":"https:\/\/ss3.4sqi.net\/img\/categories_v2\/nightlife\/pub_bg_512.png"},"is_verified":false},"comments":{"total_count":0,"count":0,"items":[]},"toasts":{"total_count":1,"count":1,"auth_toast":null,"items":[{"uid":10191865,"user":{"uid":10191865,"user_name":"WoodenAxeBrewingCo","first_name":"Wooden Axe Brewing Co","last_name":"","bio":"","location":"","relationship":"none","user_avatar":"https:\/\/assets.untappd.com\/site\/brewery_logos\/brewery-531798_e625c.jpeg","account_type":"brewery","venue_details":[],"brewery_details":{"brewery_id":531798},"user_link":"https:\/\/untappd.com\/brewery\/531798"},"like_id":1484521855,"like_owner":false,"created_at":"Mon, 25 Mar 2024 10:18:43 +0000"}]},"media":{"count":1,"items":[{"photo_id":533518288,"photo":{"photo_img_sm":"https:\/\/images.untp.beer\/crop?width=200&height=200&stripmeta=true&url=https:\/\/untappd.s3.amazonaws.com\/photos\/2024_03_24\/f4ae53f9fe0dc047ad948595aa4a2ef9_c_1366250679_raw.jpg","photo_img_md":"https:\/\/images.untp.beer\/crop?width=640&height=640&stripmeta=true&url=https:\/\/untappd.s3.amazonaws.com\/photos\/2024_03_24\/f4ae53f9fe0dc047ad948595aa4a2ef9_c_1366250679_raw.jpg","photo_img_lg":"https:\/\/images.untp.beer\/crop?width=1280&height=1280&stripmeta=true&url=https:\/\/untappd.s3.amazonaws.com\/photos\/2024_03_24\/f4ae53f9fe0dc047ad948595aa4a2ef9_c_1366250679_raw.jpg","photo_img_og":"https:\/\/assets.untappd.com\/photos\/2024_03_24\/f4ae53f9fe0dc047ad948595aa4a2ef9_c_1366250679_raw.jpg"}}]},"source":{"app_name":"Untappd for iPhone - (V2)","app_website":"http:\/\/untpd.it\/iphoneapp"},"badges":{"count":0,"items":[]}},{"checkin_id":1366250392,"created_at":"Sun, 24 Mar 2024 06:10:42 +0000","checkin_comment":"","rating_score":3.75,"user":{"uid":9266516,"user_name":"clem1903","first_name":"Clem","last_name":"Murdoch","location":"","url":"","is_supporter":0,"bio":"","relationship":null,"user_avatar":"https:\/\/assets.untappd.com\/profile\/7258f00a23b29adda33ada23cf33d2f4_100x100.jpg","is_private":0,"public_toasts":1},"beer":{"bid":5682538,"beer_name":"Off In the Woods","beer_label":"https:\/\/assets.untappd.com\/site\/beer_logos\/beer-5682538_b03d4_sm.jpeg","beer_abv":6.5,"beer_ibu":60,"beer_slug":"wooden-axe-brewing-co-off-in-the-woods","beer_description":"Introducing our West Coast IPA, generously double dry-hopped with Azacca, Idaho 7 & Strata hops. This hop trifecta delivers a burst of tropical fruit, citrus, and dank pine notes. With a crisp, clean malt backbone and a refreshing bitterness, this beer is a vibrant homage to the Pacific-Northwest's hop-rich landscapes. Dank, Piney & Resinous... Can't beat it!","beer_style":"IPA - American","has_had":false,"beer_active":1},"brewery":{"brewery_id":531798,"brewery_name":"Wooden Axe Brewing Co","brewery_slug":"wooden-axe-brewing-co","brewery_page_url":"\/WoodenAxeBrewingCo","brewery_label":"https:\/\/assets.untappd.com\/site\/brewery_logos\/brewery-531798_e625c.jpeg","country_name":"Australia","contact":{"twitter":"","facebook":"","url":"http:\/\/www.woodenaxe.beer"},"location":{"brewery_city":"","brewery_state":"","lat":0,"lng":0},"brewery_active":1},"venue":{"venue_id":656676,"venue_name":"Quarrymans Hotel","venue_slug":"quarrymans-hotel","primary_category_key":null,"primary_category":null,"parent_category_id":"4d4b7105d754a06376d81259","categories":{"count":3,"items":[{"category_key":"pub","category_name":"Pub","category_id":"4bf58dd8d48988d11b941735","is_primary":true},{"category_key":"beer_garden","category_name":"Beer Garden","category_id":"4bf58dd8d48988d117941735","is_primary":false},{"category_key":"rooftop_bar","category_name":"rooftop_bar","category_id":"5f2c224bb6d05514c70440a3","is_primary":false}]},"location":{"venue_address":"214-216 Harris St","venue_city":"Pyrmont","venue_state":"NSW","venue_country":"Australia","lat":-33.871067,"lng":151.1949921},"contact":{"twitter":"@quarrymanshotel","venue_url":"https:\/\/www.quarrymans.com.au"},"foursquare":{"foursquare_id":"4b84ad0df964a520bc4031e3","foursquare_url":"http:\/\/4sq.com\/91CEew"},"venue_icon":{"sm":"https:\/\/assets.untappd.com\/venuelogos\/venue_656676_c4e11fba_bg_64.png","md":"https:\/\/assets.untappd.com\/venuelogos\/venue_656676_c4e11fba_bg_88.png","lg":"https:\/\/assets.untappd.com\/venuelogos\/venue_656676_c4e11fba_bg_176.png?v=1"},"is_verified":true},"comments":{"total_count":0,"count":0,"items":[]},"toasts":{"total_count":1,"count":1,"auth_toast":null,"items":[{"uid":10191865,"user":{"uid":10191865,"user_name":"WoodenAxeBrewingCo","first_name":"Wooden Axe Brewing Co","last_name":"","bio":"","location":"","relationship":"none","user_avatar":"https:\/\/assets.untappd.com\/site\/brewery_logos\/brewery-531798_e625c.jpeg","account_type":"brewery","venue_details":[],"brewery_details":{"brewery_id":531798},"user_link":"https:\/\/untappd.com\/brewery\/531798"},"like_id":1484521865,"like_owner":false,"created_at":"Mon, 25 Mar 2024 10:18:46 +0000"}]},"media":{"count":0,"items":[]},"source":{"app_name":"Untappd for Android - (V4)","app_website":"http:\/\/untpd.it\/androidapp"},"badges":{"count":0,"items":[]}},{"checkin_id":1366002868,"created_at":"Sat, 23 Mar 2024 20:02:28 +0000","checkin_comment":"Mitgebracht von hb und am aus Australien. \nHopfig aber leicht. Süße wie bei alkoholfreien","rating_score":3.5,"user":{"uid":3731399,"user_name":"SchlickEtAaf","first_name":"Jonas","last_name":"Hämmer","location":"","url":"","is_supporter":0,"bio":"","relationship":null,"user_avatar":"https:\/\/assets.untappd.com\/profile\/290d88a8019a328cad60b2f1d5b993eb_100x100.jpeg","is_private":0,"public_toasts":1},"beer":{"bid":5682538,"beer_name":"Off In the Woods","beer_label":"https:\/\/assets.untappd.com\/site\/beer_logos\/beer-5682538_b03d4_sm.jpeg","beer_abv":6.5,"beer_ibu":60,"beer_slug":"wooden-axe-brewing-co-off-in-the-woods","beer_description":"Introducing our West Coast IPA, generously double dry-hopped with Azacca, Idaho 7 & Strata hops. This hop trifecta delivers a burst of tropical fruit, citrus, and dank pine notes. With a crisp, clean malt backbone and a refreshing bitterness, this beer is a vibrant homage to the Pacific-Northwest's hop-rich landscapes. Dank, Piney & Resinous... Can't beat it!","beer_style":"IPA - American","has_had":false,"beer_active":1},"brewery":{"brewery_id":531798,"brewery_name":"Wooden Axe Brewing Co","brewery_slug":"wooden-axe-brewing-co","brewery_page_url":"\/WoodenAxeBrewingCo","brewery_label":"https:\/\/assets.untappd.com\/site\/brewery_logos\/brewery-531798_e625c.jpeg","country_name":"Australia","contact":{"twitter":"","facebook":"","url":"http:\/\/www.woodenaxe.beer"},"location":{"brewery_city":"","brewery_state":"","lat":0,"lng":0},"brewery_active":1},"venue":[],"comments":{"total_count":0,"count":0,"items":[]},"toasts":{"total_count":1,"count":1,"auth_toast":null,"items":[{"uid":10191865,"user":{"uid":10191865,"user_name":"WoodenAxeBrewingCo","first_name":"Wooden Axe Brewing Co","last_name":"","bio":"","location":"","relationship":"none","user_avatar":"https:\/\/assets.untappd.com\/site\/brewery_logos\/brewery-531798_e625c.jpeg","account_type":"brewery","venue_details":[],"brewery_details":{"brewery_id":531798},"user_link":"https:\/\/untappd.com\/brewery\/531798"},"like_id":1484521874,"like_owner":false,"created_at":"Mon, 25 Mar 2024 10:18:48 +0000"}]},"media":{"count":1,"items":[{"photo_id":533393286,"photo":{"photo_img_sm":"https:\/\/images.untp.beer\/crop?width=200&height=200&stripmeta=true&url=https:\/\/untappd.s3.amazonaws.com\/photos\/2024_03_23\/faa3819d10ec83c0e8cdd12c557b580f_c_1366002868_raw.jpg","photo_img_md":"https:\/\/images.untp.beer\/crop?width=640&height=640&stripmeta=true&url=https:\/\/untappd.s3.amazonaws.com\/photos\/2024_03_23\/faa3819d10ec83c0e8cdd12c557b580f_c_1366002868_raw.jpg","photo_img_lg":"https:\/\/images.untp.beer\/crop?width=1280&height=1280&stripmeta=true&url=https:\/\/untappd.s3.amazonaws.com\/photos\/2024_03_23\/faa3819d10ec83c0e8cdd12c557b580f_c_1366002868_raw.jpg","photo_img_og":"https:\/\/assets.untappd.com\/photos\/2024_03_23\/faa3819d10ec83c0e8cdd12c557b580f_c_1366002868_raw.jpg"}}]},"source":{"app_name":"Untappd for Android - (V2)","app_website":"http:\/\/untpd.it\/androidapp"},"badges":{"retro_status":false,"count":1,"items":[{"badge_id":133371,"user_badge_id":1188568618,"badge_name":"For the Can (Level 18)","badge_description":"Canning is all the rage and it's not hard to see why - travels well, more environmentally friendly, and no need to carry your bottle opener. That's 90 checkins with the serving style of Can. Try 5 more for Level 19! Want to learn more about this badge? Check out our <a rel=\"link-out\" href=\"https:\/\/www.youtube.com\/watch?v=hynmM3Sb83s&t=1s\">podcast<\/a>","created_at":"Sat, 23 Mar 2024 20:02:30 +0000","badge_image":{"sm":"https:\/\/assets.untappd.com\/badges\/bdg_GloryCan_sm.jpg","md":"https:\/\/assets.untappd.com\/badges\/bdg_GloryCan_md.jpg","lg":"https:\/\/assets.untappd.com\/badges\/bdg_GloryCan_lg.jpg"}}]}},{"checkin_id":1365695260,"created_at":"Sat, 23 Mar 2024 01:52:39 +0000","checkin_comment":"","rating_score":4,"user":{"uid":3886355,"user_name":"jimbob_plumm","first_name":"JimBob","last_name":"Plummer","location":"","url":"","is_supporter":0,"bio":"","relationship":null,"user_avatar":"https:\/\/assets.untappd.com\/profile\/9e697465661916c0a3b29cefefcb923b_100x100.jpg","is_private":0,"public_toasts":1},"beer":{"bid":5487608,"beer_name":"Phase 2","beer_label":"https:\/\/assets.untappd.com\/site\/beer_logos\/beer-5487608_ebe9b_sm.jpeg","beer_abv":6.5,"beer_ibu":63,"beer_slug":"wooden-axe-brewing-co-phase-2","beer_description":"This beer is dark, hoppy and roasted.\r\nThe rye malt lends a spicy zest, perfectly complementing the citrusy hop character from some big hitters, Citra & Amarillo. This is Phase 2...","beer_style":"IPA - Black \/ Cascadian Dark Ale","has_had":false,"beer_active":1},"brewery":{"brewery_id":531798,"brewery_name":"Wooden Axe Brewing Co","brewery_slug":"wooden-axe-brewing-co","brewery_page_url":"\/WoodenAxeBrewingCo","brewery_label":"https:\/\/assets.untappd.com\/site\/brewery_logos\/brewery-531798_e625c.jpeg","country_name":"Australia","contact":{"twitter":"","facebook":"","url":"http:\/\/www.woodenaxe.beer"},"location":{"brewery_city":"","brewery_state":"","lat":0,"lng":0},"brewery_active":1},"venue":{"venue_id":9917985,"venue_name":"Untappd at Home","venue_slug":"at-home","primary_category_key":null,"primary_category":null,"parent_category_id":"4e67e38e036454776db1fb3a","categories":{"count":1,"items":[{"category_key":"home_private","category_name":"Home (private)","category_id":"4bf58dd8d48988d103941735","is_primary":true}]},"location":{"venue_address":"","venue_city":"","venue_state":"NC","venue_country":"United States","lat":34.2346611,"lng":-77.9482117},"contact":{"twitter":"","venue_url":""},"foursquare":{"foursquare_id":"5e7b4d99c91df60008e8b168","foursquare_url":"https:\/\/4sq.com\/3bDWYuq"},"venue_icon":{"sm":"https:\/\/assets.untappd.com\/venuelogos\/venue_9917985_b3a5d245_bg_64.png","md":"https:\/\/assets.untappd.com\/venuelogos\/venue_9917985_b3a5d245_bg_88.png","lg":"https:\/\/assets.untappd.com\/venuelogos\/venue_9917985_b3a5d245_bg_176.png?v=1"},"is_verified":true},"comments":{"total_count":0,"count":0,"items":[]},"toasts":{"total_count":1,"count":1,"auth_toast":null,"items":[{"uid":10191865,"user":{"uid":10191865,"user_name":"WoodenAxeBrewingCo","first_name":"Wooden Axe Brewing Co","last_name":"","bio":"","location":"","relationship":"none","user_avatar":"https:\/\/assets.untappd.com\/site\/brewery_logos\/brewery-531798_e625c.jpeg","account_type":"brewery","venue_details":[],"brewery_details":{"brewery_id":531798},"user_link":"https:\/\/untappd.com\/brewery\/531798"},"like_id":1484521757,"like_owner":false,"created_at":"Mon, 25 Mar 2024 10:18:03 +0000"}]},"media":{"count":1,"items":[{"photo_id":533218733,"photo":{"photo_img_sm":"https:\/\/images.untp.beer\/crop?width=200&height=200&stripmeta=true&url=https:\/\/untappd.s3.amazonaws.com\/photos\/2024_03_23\/0c56abc3e804257c0e895c0f380f9f3d_c_1365695260_raw.jpg","photo_img_md":"https:\/\/images.untp.beer\/crop?width=640&height=640&stripmeta=true&url=https:\/\/untappd.s3.amazonaws.com\/photos\/2024_03_23\/0c56abc3e804257c0e895c0f380f9f3d_c_1365695260_raw.jpg","photo_img_lg":"https:\/\/images.untp.beer\/crop?width=1280&height=1280&stripmeta=true&url=https:\/\/untappd.s3.amazonaws.com\/photos\/2024_03_23\/0c56abc3e804257c0e895c0f380f9f3d_c_1365695260_raw.jpg","photo_img_og":"https:\/\/assets.untappd.com\/photos\/2024_03_23\/0c56abc3e804257c0e895c0f380f9f3d_c_1365695260_raw.jpg"}}]},"source":{"app_name":"Untappd for iPhone - (V2)","app_website":"http:\/\/untpd.it\/iphoneapp"},"badges":{"count":0,"items":[]}},{"checkin_id":1365340181,"created_at":"Fri, 22 Mar 2024 10:14:29 +0000","checkin_comment":"So, what is a West Coast IPA? Last week it was Hazy. This week ... just hoppy like an IPA. Good drinking though 😊","rating_score":4,"user":{"uid":2921473,"user_name":"JohnLear","first_name":"John","last_name":"Lear","location":"","url":"","is_supporter":0,"bio":"","relationship":null,"user_avatar":"https:\/\/assets.untappd.com\/profile\/6bda0e6cb783f97fdf8dae38437c411f_100x100.jpg","is_private":0,"public_toasts":1},"beer":{"bid":5682538,"beer_name":"Off In the Woods","beer_label":"https:\/\/assets.untappd.com\/site\/beer_logos\/beer-5682538_b03d4_sm.jpeg","beer_abv":6.5,"beer_ibu":60,"beer_slug":"wooden-axe-brewing-co-off-in-the-woods","beer_description":"Introducing our West Coast IPA, generously double dry-hopped with Azacca, Idaho 7 & Strata hops. This hop trifecta delivers a burst of tropical fruit, citrus, and dank pine notes. With a crisp, clean malt backbone and a refreshing bitterness, this beer is a vibrant homage to the Pacific-Northwest's hop-rich landscapes. Dank, Piney & Resinous... Can't beat it!","beer_style":"IPA - American","has_had":false,"beer_active":1},"brewery":{"brewery_id":531798,"brewery_name":"Wooden Axe Brewing Co","brewery_slug":"wooden-axe-brewing-co","brewery_page_url":"\/WoodenAxeBrewingCo","brewery_label":"https:\/\/assets.untappd.com\/site\/brewery_logos\/brewery-531798_e625c.jpeg","country_name":"Australia","contact":{"twitter":"","facebook":"","url":"http:\/\/www.woodenaxe.beer"},"location":{"brewery_city":"","brewery_state":"","lat":0,"lng":0},"brewery_active":1},"venue":{"venue_id":9917985,"venue_name":"Untappd at Home","venue_slug":"at-home","primary_category_key":null,"primary_category":null,"parent_category_id":"4e67e38e036454776db1fb3a","categories":{"count":1,"items":[{"category_key":"home_private","category_name":"Home (private)","category_id":"4bf58dd8d48988d103941735","is_primary":true}]},"location":{"venue_address":"","venue_city":"","venue_state":"NC","venue_country":"United States","lat":34.2346611,"lng":-77.9482117},"contact":{"twitter":"","venue_url":""},"foursquare":{"foursquare_id":"5e7b4d99c91df60008e8b168","foursquare_url":"https:\/\/4sq.com\/3bDWYuq"},"venue_icon":{"sm":"https:\/\/assets.untappd.com\/venuelogos\/venue_9917985_b3a5d245_bg_64.png","md":"https:\/\/assets.untappd.com\/venuelogos\/venue_9917985_b3a5d245_bg_88.png","lg":"https:\/\/assets.untappd.com\/venuelogos\/venue_9917985_b3a5d245_bg_176.png?v=1"},"is_verified":true},"comments":{"total_count":0,"count":0,"items":[]},"toasts":{"total_count":1,"count":1,"auth_toast":null,"items":[{"uid":10191865,"user":{"uid":10191865,"user_name":"WoodenAxeBrewingCo","first_name":"Wooden Axe Brewing Co","last_name":"","bio":"","location":"","relationship":"none","user_avatar":"https:\/\/assets.untappd.com\/site\/brewery_logos\/brewery-531798_e625c.jpeg","account_type":"brewery","venue_details":[],"brewery_details":{"brewery_id":531798},"user_link":"https:\/\/untappd.com\/brewery\/531798"},"like_id":1484521893,"like_owner":false,"created_at":"Mon, 25 Mar 2024 10:18:52 +0000"}]},"media":{"count":1,"items":[{"photo_id":533020372,"photo":{"photo_img_sm":"https:\/\/images.untp.beer\/crop?width=200&height=200&stripmeta=true&url=https:\/\/untappd.s3.amazonaws.com\/photos\/2024_03_22\/cb2eef498ce39060998d6cf6f5c33f22_c_1365340181_raw.jpg","photo_img_md":"https:\/\/images.untp.beer\/crop?width=640&height=640&stripmeta=true&url=https:\/\/untappd.s3.amazonaws.com\/photos\/2024_03_22\/cb2eef498ce39060998d6cf6f5c33f22_c_1365340181_raw.jpg","photo_img_lg":"https:\/\/images.untp.beer\/crop?width=1280&height=1280&stripmeta=true&url=https:\/\/untappd.s3.amazonaws.com\/photos\/2024_03_22\/cb2eef498ce39060998d6cf6f5c33f22_c_1365340181_raw.jpg","photo_img_og":"https:\/\/assets.untappd.com\/photos\/2024_03_22\/cb2eef498ce39060998d6cf6f5c33f22_c_1365340181_raw.jpg"}}]},"source":{"app_name":"Untappd for Android - (V2)","app_website":"http:\/\/untpd.it\/androidapp"},"badges":{"retro_status":false,"count":1,"items":[{"badge_id":418063,"user_badge_id":1187953853,"badge_name":"Untappd at Home (Level 69)","badge_description":"Thanks for staying at home, and checking in with Untappd! It allows us to stay connected to a community of beer lovers, just like you, even if we can't be in the same physical location. From our home to yours, cheers and stay safe!","created_at":"Fri, 22 Mar 2024 10:14:29 +0000","badge_image":{"sm":"https:\/\/assets.untappd.com\/badges\/bdg_untappdAtHome_sm.jpg","md":"https:\/\/assets.untappd.com\/badges\/bdg_untappdAtHome_md.jpg","lg":"https:\/\/assets.untappd.com\/badges\/bdg_untappdAtHome_lg.jpg"}}]}},{"checkin_id":1365337419,"created_at":"Fri, 22 Mar 2024 08:57:04 +0000","checkin_comment":"","rating_score":4,"user":{"uid":3822716,"user_name":"shaunms","first_name":"Shaun","last_name":"Simon","location":"","url":"","is_supporter":0,"bio":"","relationship":null,"user_avatar":"https:\/\/gravatar.com\/avatar\/646422d1ba98e5d5ad8a2e7aa8e827a9?size=100&d=https%3A%2F%2Fassets.untappd.com%2Fsite%2Fassets%2Fimages%2Fdefault_avatar_v3_gravatar.jpg%3Fv%3D2","is_private":0,"public_toasts":1},"beer":{"bid":5682538,"beer_name":"Off In the Woods","beer_label":"https:\/\/assets.untappd.com\/site\/beer_logos\/beer-5682538_b03d4_sm.jpeg","beer_abv":6.5,"beer_ibu":60,"beer_slug":"wooden-axe-brewing-co-off-in-the-woods","beer_description":"Introducing our West Coast IPA, generously double dry-hopped with Azacca, Idaho 7 & Strata hops. This hop trifecta delivers a burst of tropical fruit, citrus, and dank pine notes. With a crisp, clean malt backbone and a refreshing bitterness, this beer is a vibrant homage to the Pacific-Northwest's hop-rich landscapes. Dank, Piney & Resinous... Can't beat it!","beer_style":"IPA - American","has_had":false,"beer_active":1},"brewery":{"brewery_id":531798,"brewery_name":"Wooden Axe Brewing Co","brewery_slug":"wooden-axe-brewing-co","brewery_page_url":"\/WoodenAxeBrewingCo","brewery_label":"https:\/\/assets.untappd.com\/site\/brewery_logos\/brewery-531798_e625c.jpeg","country_name":"Australia","contact":{"twitter":"","facebook":"","url":"http:\/\/www.woodenaxe.beer"},"location":{"brewery_city":"","brewery_state":"","lat":0,"lng":0},"brewery_active":1},"venue":[],"comments":{"total_count":0,"count":0,"items":[]},"toasts":{"total_count":1,"count":1,"auth_toast":null,"items":[{"uid":10191865,"user":{"uid":10191865,"user_name":"WoodenAxeBrewingCo","first_name":"Wooden Axe Brewing Co","last_name":"","bio":"","location":"","relationship":"none","user_avatar":"https:\/\/assets.untappd.com\/site\/brewery_logos\/brewery-531798_e625c.jpeg","account_type":"brewery","venue_details":[],"brewery_details":{"brewery_id":531798},"user_link":"https:\/\/untappd.com\/brewery\/531798"},"like_id":1484521904,"like_owner":false,"created_at":"Mon, 25 Mar 2024 10:18:56 +0000"}]},"media":{"count":0,"items":[]},"source":{"app_name":"Untappd for Android - (V4)","app_website":"http:\/\/untpd.it\/androidapp"},"badges":{"count":0,"items":[]}},{"checkin_id":1365314495,"created_at":"Fri, 22 Mar 2024 02:15:09 +0000","checkin_comment":"","rating_score":3.75,"user":{"uid":994340,"user_name":"philclement","first_name":"Phil","last_name":"Clement","location":"Sydney, Australia","url":"","is_supporter":0,"bio":"ALL THE BEERS","relationship":null,"user_avatar":"https:\/\/assets.untappd.com\/profile\/8dfddc21ba151eafea54c0967caf5f74_100x100.jpg","is_private":0,"public_toasts":1},"beer":{"bid":5682538,"beer_name":"Off In the Woods","beer_label":"https:\/\/assets.untappd.com\/site\/beer_logos\/beer-5682538_b03d4_sm.jpeg","beer_abv":6.5,"beer_ibu":60,"beer_slug":"wooden-axe-brewing-co-off-in-the-woods","beer_description":"Introducing our West Coast IPA, generously double dry-hopped with Azacca, Idaho 7 & Strata hops. This hop trifecta delivers a burst of tropical fruit, citrus, and dank pine notes. With a crisp, clean malt backbone and a refreshing bitterness, this beer is a vibrant homage to the Pacific-Northwest's hop-rich landscapes. Dank, Piney & Resinous... Can't beat it!","beer_style":"IPA - American","has_had":false,"beer_active":1},"brewery":{"brewery_id":531798,"brewery_name":"Wooden Axe Brewing Co","brewery_slug":"wooden-axe-brewing-co","brewery_page_url":"\/WoodenAxeBrewingCo","brewery_label":"https:\/\/assets.untappd.com\/site\/brewery_logos\/brewery-531798_e625c.jpeg","country_name":"Australia","contact":{"twitter":"","facebook":"","url":"http:\/\/www.woodenaxe.beer"},"location":{"brewery_city":"","brewery_state":"","lat":0,"lng":0},"brewery_active":1},"venue":{"venue_id":11123297,"venue_name":"Mixtape Brewing and Bar","venue_slug":"mixtape-brewing-and-bar","primary_category_key":null,"primary_category":null,"parent_category_id":"4d4b7105d754a06376d81259","categories":{"count":4,"items":[{"category_key":"brewery","category_name":"Brewery","category_id":"50327c8591d4c4b30a586d5d","is_primary":true},{"category_key":"bar","category_name":"Bar","category_id":"4bf58dd8d48988d116941735","is_primary":false},{"category_key":"food_court","category_name":"Food Court","category_id":"4bf58dd8d48988d120951735","is_primary":false},{"category_key":"food","category_name":"Restaurant","category_id":"4d4b7105d754a06374d81259","is_primary":false}]},"location":{"venue_address":"142A Victoria Road","venue_city":"Marrickville","venue_state":"NSW","venue_country":"Australia","lat":-33.9072151,"lng":151.1645355},"contact":{"twitter":"","venue_url":"http:\/\/mixtapebrewing.com.au\/"},"foursquare":{"foursquare_id":"6203bd2c962fd731b6c885bf","foursquare_url":"https:\/\/4sq.com\/3HFRjVl"},"venue_icon":{"sm":"https:\/\/assets.untappd.com\/venuelogos\/venue_11123297_03f44aaa_bg_64.png","md":"https:\/\/assets.untappd.com\/venuelogos\/venue_11123297_03f44aaa_bg_88.png","lg":"https:\/\/assets.untappd.com\/venuelogos\/venue_11123297_03f44aaa_bg_176.png?v=1"},"is_verified":true},"comments":{"total_count":0,"count":0,"items":[]},"toasts":{"total_count":2,"count":1,"auth_toast":null,"items":[{"uid":10191865,"user":{"uid":10191865,"user_name":"WoodenAxeBrewingCo","first_name":"Wooden Axe Brewing Co","last_name":"","bio":"","location":"","relationship":"none","user_avatar":"https:\/\/assets.untappd.com\/site\/brewery_logos\/brewery-531798_e625c.jpeg","account_type":"brewery","venue_details":[],"brewery_details":{"brewery_id":531798},"user_link":"https:\/\/untappd.com\/brewery\/531798"},"like_id":1484521908,"like_owner":false,"created_at":"Mon, 25 Mar 2024 10:18:57 +0000"}]},"media":{"count":0,"items":[]},"source":{"app_name":"Untappd for Android - (V2)","app_website":"http:\/\/untpd.it\/androidapp"},"badges":{"count":0,"items":[]}},{"checkin_id":1365108331,"created_at":"Thu, 21 Mar 2024 05:50:53 +0000","checkin_comment":"","rating_score":3.75,"user":{"uid":10549720,"user_name":"aviewandabeer","first_name":"Andrew","last_name":"Frith","location":"Greta NSW Australia ","url":"","is_supporter":0,"bio":"Insta: aviewandabeer","relationship":null,"user_avatar":"https:\/\/assets.untappd.com\/profile\/a25735ace14c81c25f44e89c3ad97422_100x100.jpg","is_private":0,"public_toasts":1},"beer":{"bid":5682538,"beer_name":"Off In the Woods","beer_label":"https:\/\/assets.untappd.com\/site\/beer_logos\/beer-5682538_b03d4_sm.jpeg","beer_abv":6.5,"beer_ibu":60,"beer_slug":"wooden-axe-brewing-co-off-in-the-woods","beer_description":"Introducing our West Coast IPA, generously double dry-hopped with Azacca, Idaho 7 & Strata hops. This hop trifecta delivers a burst of tropical fruit, citrus, and dank pine notes. With a crisp, clean malt backbone and a refreshing bitterness, this beer is a vibrant homage to the Pacific-Northwest's hop-rich landscapes. Dank, Piney & Resinous... Can't beat it!","beer_style":"IPA - American","has_had":false,"beer_active":1},"brewery":{"brewery_id":531798,"brewery_name":"Wooden Axe Brewing Co","brewery_slug":"wooden-axe-brewing-co","brewery_page_url":"\/WoodenAxeBrewingCo","brewery_label":"https:\/\/assets.untappd.com\/site\/brewery_logos\/brewery-531798_e625c.jpeg","country_name":"Australia","contact":{"twitter":"","facebook":"","url":"http:\/\/www.woodenaxe.beer"},"location":{"brewery_city":"","brewery_state":"","lat":0,"lng":0},"brewery_active":1},"venue":{"venue_id":9917985,"venue_name":"Untappd at Home","venue_slug":"at-home","primary_category_key":null,"primary_category":null,"parent_category_id":"4e67e38e036454776db1fb3a","categories":{"count":1,"items":[{"category_key":"home_private","category_name":"Home (private)","category_id":"4bf58dd8d48988d103941735","is_primary":true}]},"location":{"venue_address":"","venue_city":"","venue_state":"NC","venue_country":"United States","lat":34.2346611,"lng":-77.9482117},"contact":{"twitter":"","venue_url":""},"foursquare":{"foursquare_id":"5e7b4d99c91df60008e8b168","foursquare_url":"https:\/\/4sq.com\/3bDWYuq"},"venue_icon":{"sm":"https:\/\/assets.untappd.com\/venuelogos\/venue_9917985_b3a5d245_bg_64.png","md":"https:\/\/assets.untappd.com\/venuelogos\/venue_9917985_b3a5d245_bg_88.png","lg":"https:\/\/assets.untappd.com\/venuelogos\/venue_9917985_b3a5d245_bg_176.png?v=1"},"is_verified":true},"comments":{"total_count":0,"count":0,"items":[]},"toasts":{"total_count":1,"count":1,"auth_toast":null,"items":[{"uid":10191865,"user":{"uid":10191865,"user_name":"WoodenAxeBrewingCo","first_name":"Wooden Axe Brewing Co","last_name":"","bio":"","location":"","relationship":"none","user_avatar":"https:\/\/assets.untappd.com\/site\/brewery_logos\/brewery-531798_e625c.jpeg","account_type":"brewery","venue_details":[],"brewery_details":{"brewery_id":531798},"user_link":"https:\/\/untappd.com\/brewery\/531798"},"like_id":1484521912,"like_owner":false,"created_at":"Mon, 25 Mar 2024 10:18:59 +0000"}]},"media":{"count":1,"items":[{"photo_id":532896932,"photo":{"photo_img_sm":"https:\/\/images.untp.beer\/crop?width=200&height=200&stripmeta=true&url=https:\/\/untappd.s3.amazonaws.com\/photos\/2024_03_21\/1059412c155f9973e79f14493c5864e9_c_1365108331_raw.jpg","photo_img_md":"https:\/\/images.untp.beer\/crop?width=640&height=640&stripmeta=true&url=https:\/\/untappd.s3.amazonaws.com\/photos\/2024_03_21\/1059412c155f9973e79f14493c5864e9_c_1365108331_raw.jpg","photo_img_lg":"https:\/\/images.untp.beer\/crop?width=1280&height=1280&stripmeta=true&url=https:\/\/untappd.s3.amazonaws.com\/photos\/2024_03_21\/1059412c155f9973e79f14493c5864e9_c_1365108331_raw.jpg","photo_img_og":"https:\/\/assets.untappd.com\/photos\/2024_03_21\/1059412c155f9973e79f14493c5864e9_c_1365108331_raw.jpg"}}]},"source":{"app_name":"Untappd for iPhone - (V4)","app_website":"http:\/\/untpd.it\/iphoneapp"},"badges":{"retro_status":false,"count":1,"items":[{"badge_id":243526,"user_badge_id":1187734004,"badge_name":"Brewery Pioneer (Level 31)","badge_description":"There's beer in them thar hills! You're setting off on your journey through the world of beer, but be sure to take a little time to get to know each brewery as you go. That's a beer from 155 different breweries. Try 5 more for Level 32!","created_at":"Thu, 21 Mar 2024 05:50:54 +0000","badge_image":{"sm":"https:\/\/assets.untappd.com\/badges\/bdg_brewery_prioneer_sm.jpg","md":"https:\/\/assets.untappd.com\/badges\/bdg_brewery_prioneer_sm.jpg","lg":"https:\/\/assets.untappd.com\/badges\/bdg_brewery_prioneer_sm.jpg"}}]}},{"checkin_id":1364945204,"created_at":"Wed, 20 Mar 2024 10:00:10 +0000","checkin_comment":"What flavour there is is fine, but would like a bit more oomph in a 6.5% WCIPA.","rating_score":3.25,"user":{"uid":1496,"user_name":"rohangifford","first_name":"Rohan","last_name":"Gifford","location":"Sydney, Australia","url":"","is_supporter":0,"bio":"","relationship":null,"user_avatar":"https:\/\/assets.untappd.com\/profile\/86becdff4a1caf9a130b8e8d1d6fd389_thumb.png","is_private":0,"public_toasts":1},"beer":{"bid":5682538,"beer_name":"Off In the Woods","beer_label":"https:\/\/assets.untappd.com\/site\/beer_logos\/beer-5682538_b03d4_sm.jpeg","beer_abv":6.5,"beer_ibu":60,"beer_slug":"wooden-axe-brewing-co-off-in-the-woods","beer_description":"Introducing our West Coast IPA, generously double dry-hopped with Azacca, Idaho 7 & Strata hops. This hop trifecta delivers a burst of tropical fruit, citrus, and dank pine notes. With a crisp, clean malt backbone and a refreshing bitterness, this beer is a vibrant homage to the Pacific-Northwest's hop-rich landscapes. Dank, Piney & Resinous... Can't beat it!","beer_style":"IPA - American","has_had":false,"beer_active":1},"brewery":{"brewery_id":531798,"brewery_name":"Wooden Axe Brewing Co","brewery_slug":"wooden-axe-brewing-co","brewery_page_url":"\/WoodenAxeBrewingCo","brewery_label":"https:\/\/assets.untappd.com\/site\/brewery_logos\/brewery-531798_e625c.jpeg","country_name":"Australia","contact":{"twitter":"","facebook":"","url":"http:\/\/www.woodenaxe.beer"},"location":{"brewery_city":"","brewery_state":"","lat":0,"lng":0},"brewery_active":1},"venue":{"venue_id":656676,"venue_name":"Quarrymans Hotel","venue_slug":"quarrymans-hotel","primary_category_key":null,"primary_category":null,"parent_category_id":"4d4b7105d754a06376d81259","categories":{"count":3,"items":[{"category_key":"pub","category_name":"Pub","category_id":"4bf58dd8d48988d11b941735","is_primary":true},{"category_key":"beer_garden","category_name":"Beer Garden","category_id":"4bf58dd8d48988d117941735","is_primary":false},{"category_key":"rooftop_bar","category_name":"rooftop_bar","category_id":"5f2c224bb6d05514c70440a3","is_primary":false}]},"location":{"venue_address":"214-216 Harris St","venue_city":"Pyrmont","venue_state":"NSW","venue_country":"Australia","lat":-33.871067,"lng":151.1949921},"contact":{"twitter":"@quarrymanshotel","venue_url":"https:\/\/www.quarrymans.com.au"},"foursquare":{"foursquare_id":"4b84ad0df964a520bc4031e3","foursquare_url":"http:\/\/4sq.com\/91CEew"},"venue_icon":{"sm":"https:\/\/assets.untappd.com\/venuelogos\/venue_656676_c4e11fba_bg_64.png","md":"https:\/\/assets.untappd.com\/venuelogos\/venue_656676_c4e11fba_bg_88.png","lg":"https:\/\/assets.untappd.com\/venuelogos\/venue_656676_c4e11fba_bg_176.png?v=1"},"is_verified":true},"comments":{"total_count":0,"count":0,"items":[]},"toasts":{"total_count":1,"count":1,"auth_toast":null,"items":[{"uid":10191865,"user":{"uid":10191865,"user_name":"WoodenAxeBrewingCo","first_name":"Wooden Axe Brewing Co","last_name":"","bio":"","location":"","relationship":"none","user_avatar":"https:\/\/assets.untappd.com\/site\/brewery_logos\/brewery-531798_e625c.jpeg","account_type":"brewery","venue_details":[],"brewery_details":{"brewery_id":531798},"user_link":"https:\/\/untappd.com\/brewery\/531798"},"like_id":1484521926,"like_owner":false,"created_at":"Mon, 25 Mar 2024 10:19:02 +0000"}]},"media":{"count":0,"items":[]},"source":{"app_name":"Untappd for Android - (V2)","app_website":"http:\/\/untpd.it\/androidapp"},"badges":{"retro_status":false,"count":2,"items":[{"badge_id":5598,"user_badge_id":1187584095,"badge_name":"Verified Adventure (Level 18)","badge_description":"While spontaneity can be fun, sometimes you want to make sure your adventure will rock. Checkout the menu at an Untappd Verified Venue before visiting and know exactly what’s on tap! That's 90 check-ins at venue that is verified. Try 5 more for Level 19!","created_at":"Wed, 20 Mar 2024 10:00:11 +0000","badge_image":{"sm":"https:\/\/assets.untappd.com\/badges\/bdg_VerifiedVenue_sm.jpg","md":"https:\/\/assets.untappd.com\/badges\/bdg_VerifiedVenue_md.jpg","lg":"https:\/\/assets.untappd.com\/badges\/bdg_VerifiedVenue_lg.jpg"}},{"badge_id":133257,"user_badge_id":1187584096,"badge_name":"Draft City (Level 4)","badge_description":"Fresh from the tap is one of the best ways to enjoy a beer. Just try to use a glass and not drink directly from the tap, as tempting as it may be. That's 20 checkins with the serving style of Draft. Try 5 more for Level 5!","created_at":"Wed, 20 Mar 2024 10:00:11 +0000","badge_image":{"sm":"https:\/\/assets.untappd.com\/badges\/bdg_DraftCity_sm.jpg","md":"https:\/\/assets.untappd.com\/badges\/bdg_DraftCity_md.jpg","lg":"https:\/\/assets.untappd.com\/badges\/bdg_DraftCity_lg.jpg"}}]}}],"pagination":{"since_url":"https:\/\/api.untappd.com\/v4\/brewery\/checkins\/531798?max_id=1364945204","next_url":"https:\/\/api.untappd.com\/v4\/brewery\/checkins\/531798?max_id=1364945204","max_id":1364945204},"mem":false,"time":0.004,"table":"ut_brewery_checkins"},"beer_list":{"show_all_beers":false,"has_not_had_before":false,"source":"info","total_count":3,"is_search":false,"type_id":false,"sort":false,"is_multi_type":false,"count":3,"items":[{"total_user_count":0,"has_had":null,"total_count":140,"beer":{"bid":5487608,"beer_name":"Phase 2","beer_label":"https:\/\/assets.untappd.com\/site\/beer_logos\/beer-5487608_ebe9b_sm.jpeg","beer_style":"IPA - Black \/ Cascadian Dark Ale","beer_abv":6.5,"beer_ibu":63,"beer_slug":"wooden-axe-brewing-co-phase-2","beer_description":"This beer is dark, hoppy and roasted.\r\nThe rye malt lends a spicy zest, perfectly complementing the citrusy hop character from some big hitters, Citra & Amarillo. This is Phase 2...","is_in_production":1,"created_at":"Wed, 16 Aug 2023 01:31:57 +0000","user_rating_score":0,"rating_score":3.904,"rating_count":129,"has_had":null,"on_list":false,"auth_rating":0,"wish_list":false},"brewery":{"brewery_id":531798,"brewery_name":"Wooden Axe Brewing Co","brewery_slug":"wooden-axe-brewing-co","brewery_page_url":"\/WoodenAxeBrewingCo","brewery_type":"Contract Brewery","brewery_label":"https:\/\/assets.untappd.com\/site\/brewery_logos\/brewery-531798_e625c.jpeg","country_name":"Australia","contact":{"twitter":"","facebook":"","instagram":"woodenaxebrewingco","url":"http:\/\/www.woodenaxe.beer"},"location":{"brewery_city":"","brewery_state":"","lat":0,"lng":0},"brewery_active":1},"friends":{"items":[],"count":0}},{"total_user_count":0,"has_had":null,"total_count":133,"beer":{"bid":5682538,"beer_name":"Off In the Woods","beer_label":"https:\/\/assets.untappd.com\/site\/beer_logos\/beer-5682538_b03d4_sm.jpeg","beer_style":"IPA - American","beer_abv":6.5,"beer_ibu":60,"beer_slug":"wooden-axe-brewing-co-off-in-the-woods","beer_description":"Introducing our West Coast IPA, generously double dry-hopped with Azacca, Idaho 7 & Strata hops. This hop trifecta delivers a burst of tropical fruit, citrus, and dank pine notes. With a crisp, clean malt backbone and a refreshing bitterness, this beer is a vibrant homage to the Pacific-Northwest's hop-rich landscapes. Dank, Piney & Resinous... Can't beat it!","is_in_production":1,"created_at":"Wed, 17 Jan 2024 13:44:01 +0000","user_rating_score":0,"rating_score":3.838,"rating_count":119,"has_had":null,"on_list":false,"auth_rating":0,"wish_list":false},"brewery":{"brewery_id":531798,"brewery_name":"Wooden Axe Brewing Co","brewery_slug":"wooden-axe-brewing-co","brewery_page_url":"\/WoodenAxeBrewingCo","brewery_type":"Contract Brewery","brewery_label":"https:\/\/assets.untappd.com\/site\/brewery_logos\/brewery-531798_e625c.jpeg","country_name":"Australia","contact":{"twitter":"","facebook":"","instagram":"woodenaxebrewingco","url":"http:\/\/www.woodenaxe.beer"},"location":{"brewery_city":"","brewery_state":"","lat":0,"lng":0},"brewery_active":1},"friends":{"items":[],"count":0}},{"total_user_count":0,"has_had":null,"total_count":94,"beer":{"bid":5100403,"beer_name":"Beyond Reasonable Stout","beer_label":"https:\/\/assets.untappd.com\/site\/beer_logos\/beer-5100403_00c5c_sm.jpeg","beer_style":"Stout - Imperial \/ Double White \/ Golden","beer_abv":8.5,"beer_ibu":33,"beer_slug":"wooden-axe-brewing-co-beyond-reasonable-stout","beer_description":"Rich. Smooth. Decadent. \r\nBeyond Reasonable Stout is a Nitro White Imperial Stout packed with cold-brewed coffee, cacao nibs, vanilla beans, and lactose.","is_in_production":1,"created_at":"Wed, 02 Nov 2022 04:45:42 +0000","user_rating_score":0,"rating_score":3.905,"rating_count":79,"has_had":null,"on_list":false,"auth_rating":0,"wish_list":false},"brewery":{"brewery_id":531798,"brewery_name":"Wooden Axe Brewing Co","brewery_slug":"wooden-axe-brewing-co","brewery_page_url":"\/WoodenAxeBrewingCo","brewery_type":"Contract Brewery","brewery_label":"https:\/\/assets.untappd.com\/site\/brewery_logos\/brewery-531798_e625c.jpeg","country_name":"Australia","contact":{"twitter":"","facebook":"","instagram":"woodenaxebrewingco","url":"http:\/\/www.woodenaxe.beer"},"location":{"brewery_city":"","brewery_state":"","lat":0,"lng":0},"brewery_active":1},"friends":{"items":[],"count":0}}],"collaborations":{"count":0,"items":[]},"sort_name":"Most Popular","sort_key":"most_popular"},"locations":{"count":0,"items":[]}}}}